{"mean_reward": -101.96786515805029, "trial_id": "ee86f856", "training_iteration": 0, "time_this_iter_s": 5.910414218902588, "done": false, "timesteps_total": null, "episodes_total": null, "experiment_id": "6b5c107e285b4c09bc642e2787508c14", "date": "2019-11-15_23-43-57", "timestamp": 1573861437, "time_total_s": 5.910414218902588, "pid": 13777, "hostname": "213cedb5f1ad", "node_ip": "172.18.0.3", "config": {"replay_size": 10000, "lr": 0.001, "batch_size": 32, "refresh_target_network_freq": 2000, "opt_steps_per_step": 2}, "time_since_restore": 5.910414218902588, "timesteps_since_restore": 0, "iterations_since_restore": 1}
{"mean_reward": -113.07980721960217, "trial_id": "ee86f856", "training_iteration": 1, "time_this_iter_s": 1075.8556866645813, "done": false, "timesteps_total": null, "episodes_total": null, "experiment_id": "6b5c107e285b4c09bc642e2787508c14", "date": "2019-11-16_00-01-52", "timestamp": 1573862512, "time_total_s": 1081.766100883484, "pid": 13777, "hostname": "213cedb5f1ad", "node_ip": "172.18.0.3", "config": {"replay_size": 10000, "lr": 0.001, "batch_size": 32, "refresh_target_network_freq": 2000, "opt_steps_per_step": 2}, "time_since_restore": 1081.766100883484, "timesteps_since_restore": 0, "iterations_since_restore": 2}
{"mean_reward": -117.35088171833816, "trial_id": "ee86f856", "training_iteration": 2, "time_this_iter_s": 1098.5763156414032, "done": false, "timesteps_total": null, "episodes_total": null, "experiment_id": "6b5c107e285b4c09bc642e2787508c14", "date": "2019-11-16_00-20-11", "timestamp": 1573863611, "time_total_s": 2180.342416524887, "pid": 13777, "hostname": "213cedb5f1ad", "node_ip": "172.18.0.3", "config": {"replay_size": 10000, "lr": 0.001, "batch_size": 32, "refresh_target_network_freq": 2000, "opt_steps_per_step": 2}, "time_since_restore": 2180.342416524887, "timesteps_since_restore": 0, "iterations_since_restore": 3}
{"mean_reward": -101.75609417524184, "trial_id": "ee86f856", "training_iteration": 3, "time_this_iter_s": 1068.4331285953522, "done": false, "timesteps_total": null, "episodes_total": null, "experiment_id": "6b5c107e285b4c09bc642e2787508c14", "date": "2019-11-16_00-37-59", "timestamp": 1573864679, "time_total_s": 3248.7755451202393, "pid": 13777, "hostname": "213cedb5f1ad", "node_ip": "172.18.0.3", "config": {"replay_size": 10000, "lr": 0.001, "batch_size": 32, "refresh_target_network_freq": 2000, "opt_steps_per_step": 2}, "time_since_restore": 3248.7755451202393, "timesteps_since_restore": 0, "iterations_since_restore": 4}
{"mean_reward": -99.71276735307917, "trial_id": "ee86f856", "training_iteration": 4, "time_this_iter_s": 1056.1838932037354, "done": false, "timesteps_total": null, "episodes_total": null, "experiment_id": "6b5c107e285b4c09bc642e2787508c14", "date": "2019-11-16_00-55-36", "timestamp": 1573865736, "time_total_s": 4304.959438323975, "pid": 13777, "hostname": "213cedb5f1ad", "node_ip": "172.18.0.3", "config": {"replay_size": 10000, "lr": 0.001, "batch_size": 32, "refresh_target_network_freq": 2000, "opt_steps_per_step": 2}, "time_since_restore": 4304.959438323975, "timesteps_since_restore": 0, "iterations_since_restore": 5}
{"mean_reward": -120.66692447463662, "trial_id": "ee86f856", "training_iteration": 5, "time_this_iter_s": 1031.5257103443146, "done": false, "timesteps_total": null, "episodes_total": null, "experiment_id": "6b5c107e285b4c09bc642e2787508c14", "date": "2019-11-16_01-12-47", "timestamp": 1573866767, "time_total_s": 5336.485148668289, "pid": 13777, "hostname": "213cedb5f1ad", "node_ip": "172.18.0.3", "config": {"replay_size": 10000, "lr": 0.001, "batch_size": 32, "refresh_target_network_freq": 2000, "opt_steps_per_step": 2}, "time_since_restore": 5336.485148668289, "timesteps_since_restore": 0, "iterations_since_restore": 6}
{"mean_reward": -104.62460258853724, "trial_id": "ee86f856", "training_iteration": 6, "time_this_iter_s": 1017.9104218482971, "done": false, "timesteps_total": null, "episodes_total": null, "experiment_id": "6b5c107e285b4c09bc642e2787508c14", "date": "2019-11-16_01-29-45", "timestamp": 1573867785, "time_total_s": 6354.395570516586, "pid": 13777, "hostname": "213cedb5f1ad", "node_ip": "172.18.0.3", "config": {"replay_size": 10000, "lr": 0.001, "batch_size": 32, "refresh_target_network_freq": 2000, "opt_steps_per_step": 2}, "time_since_restore": 6354.395570516586, "timesteps_since_restore": 0, "iterations_since_restore": 7}
{"mean_reward": -106.7234306057319, "trial_id": "ee86f856", "training_iteration": 7, "time_this_iter_s": 1027.5578796863556, "done": false, "timesteps_total": null, "episodes_total": null, "experiment_id": "6b5c107e285b4c09bc642e2787508c14", "date": "2019-11-16_01-46-53", "timestamp": 1573868813, "time_total_s": 7381.953450202942, "pid": 13777, "hostname": "213cedb5f1ad", "node_ip": "172.18.0.3", "config": {"replay_size": 10000, "lr": 0.001, "batch_size": 32, "refresh_target_network_freq": 2000, "opt_steps_per_step": 2}, "time_since_restore": 7381.953450202942, "timesteps_since_restore": 0, "iterations_since_restore": 8}
{"mean_reward": -111.89065116138808, "trial_id": "ee86f856", "training_iteration": 8, "time_this_iter_s": 1021.8126037120819, "done": false, "timesteps_total": null, "episodes_total": null, "experiment_id": "6b5c107e285b4c09bc642e2787508c14", "date": "2019-11-16_02-03-54", "timestamp": 1573869834, "time_total_s": 8403.766053915024, "pid": 13777, "hostname": "213cedb5f1ad", "node_ip": "172.18.0.3", "config": {"replay_size": 10000, "lr": 0.001, "batch_size": 32, "refresh_target_network_freq": 2000, "opt_steps_per_step": 2}, "time_since_restore": 8403.766053915024, "timesteps_since_restore": 0, "iterations_since_restore": 9}
{"mean_reward": -101.36143186326284, "trial_id": "ee86f856", "training_iteration": 9, "time_this_iter_s": 1028.3998682498932, "done": false, "timesteps_total": null, "episodes_total": null, "experiment_id": "6b5c107e285b4c09bc642e2787508c14", "date": "2019-11-16_02-21-03", "timestamp": 1573870863, "time_total_s": 9432.165922164917, "pid": 13777, "hostname": "213cedb5f1ad", "node_ip": "172.18.0.3", "config": {"replay_size": 10000, "lr": 0.001, "batch_size": 32, "refresh_target_network_freq": 2000, "opt_steps_per_step": 2}, "time_since_restore": 9432.165922164917, "timesteps_since_restore": 0, "iterations_since_restore": 10}
{"mean_reward": -105.44181396889542, "trial_id": "ee86f856", "training_iteration": 10, "time_this_iter_s": 1037.0744404792786, "done": false, "timesteps_total": null, "episodes_total": null, "experiment_id": "6b5c107e285b4c09bc642e2787508c14", "date": "2019-11-16_02-38-20", "timestamp": 1573871900, "time_total_s": 10469.240362644196, "pid": 13777, "hostname": "213cedb5f1ad", "node_ip": "172.18.0.3", "config": {"replay_size": 10000, "lr": 0.001, "batch_size": 32, "refresh_target_network_freq": 2000, "opt_steps_per_step": 2}, "time_since_restore": 10469.240362644196, "timesteps_since_restore": 0, "iterations_since_restore": 11}
{"mean_reward": -101.17063231011544, "trial_id": "ee86f856", "training_iteration": 11, "time_this_iter_s": 1070.4085056781769, "done": false, "timesteps_total": null, "episodes_total": null, "experiment_id": "6b5c107e285b4c09bc642e2787508c14", "date": "2019-11-16_02-56-10", "timestamp": 1573872970, "time_total_s": 11539.648868322372, "pid": 13777, "hostname": "213cedb5f1ad", "node_ip": "172.18.0.3", "config": {"replay_size": 10000, "lr": 0.001, "batch_size": 32, "refresh_target_network_freq": 2000, "opt_steps_per_step": 2}, "time_since_restore": 11539.648868322372, "timesteps_since_restore": 0, "iterations_since_restore": 12}
{"mean_reward": -112.94374071628617, "trial_id": "ee86f856", "training_iteration": 12, "time_this_iter_s": 1070.009729385376, "done": false, "timesteps_total": null, "episodes_total": null, "experiment_id": "6b5c107e285b4c09bc642e2787508c14", "date": "2019-11-16_03-14-00", "timestamp": 1573874040, "time_total_s": 12609.658597707748, "pid": 13777, "hostname": "213cedb5f1ad", "node_ip": "172.18.0.3", "config": {"replay_size": 10000, "lr": 0.001, "batch_size": 32, "refresh_target_network_freq": 2000, "opt_steps_per_step": 2}, "time_since_restore": 12609.658597707748, "timesteps_since_restore": 0, "iterations_since_restore": 13}
{"mean_reward": -119.12845737899254, "trial_id": "ee86f856", "training_iteration": 13, "time_this_iter_s": 1072.0776345729828, "done": false, "timesteps_total": null, "episodes_total": null, "experiment_id": "6b5c107e285b4c09bc642e2787508c14", "date": "2019-11-16_03-31-52", "timestamp": 1573875112, "time_total_s": 13681.736232280731, "pid": 13777, "hostname": "213cedb5f1ad", "node_ip": "172.18.0.3", "config": {"replay_size": 10000, "lr": 0.001, "batch_size": 32, "refresh_target_network_freq": 2000, "opt_steps_per_step": 2}, "time_since_restore": 13681.736232280731, "timesteps_since_restore": 0, "iterations_since_restore": 14}
{"mean_reward": -99.90373559150699, "trial_id": "ee86f856", "training_iteration": 14, "time_this_iter_s": 1053.70263838768, "done": false, "timesteps_total": null, "episodes_total": null, "experiment_id": "6b5c107e285b4c09bc642e2787508c14", "date": "2019-11-16_03-49-26", "timestamp": 1573876166, "time_total_s": 14735.438870668411, "pid": 13777, "hostname": "213cedb5f1ad", "node_ip": "172.18.0.3", "config": {"replay_size": 10000, "lr": 0.001, "batch_size": 32, "refresh_target_network_freq": 2000, "opt_steps_per_step": 2}, "time_since_restore": 14735.438870668411, "timesteps_since_restore": 0, "iterations_since_restore": 15}
{"mean_reward": -105.25902425233585, "trial_id": "ee86f856", "training_iteration": 15, "time_this_iter_s": 1045.7844343185425, "done": false, "timesteps_total": null, "episodes_total": null, "experiment_id": "6b5c107e285b4c09bc642e2787508c14", "date": "2019-11-16_04-06-52", "timestamp": 1573877212, "time_total_s": 15781.223304986954, "pid": 13777, "hostname": "213cedb5f1ad", "node_ip": "172.18.0.3", "config": {"replay_size": 10000, "lr": 0.001, "batch_size": 32, "refresh_target_network_freq": 2000, "opt_steps_per_step": 2}, "time_since_restore": 15781.223304986954, "timesteps_since_restore": 0, "iterations_since_restore": 16}
{"mean_reward": -105.0920167543906, "trial_id": "ee86f856", "training_iteration": 16, "time_this_iter_s": 1028.1636595726013, "done": false, "timesteps_total": null, "episodes_total": null, "experiment_id": "6b5c107e285b4c09bc642e2787508c14", "date": "2019-11-16_04-24-00", "timestamp": 1573878240, "time_total_s": 16809.386964559555, "pid": 13777, "hostname": "213cedb5f1ad", "node_ip": "172.18.0.3", "config": {"replay_size": 10000, "lr": 0.001, "batch_size": 32, "refresh_target_network_freq": 2000, "opt_steps_per_step": 2}, "time_since_restore": 16809.386964559555, "timesteps_since_restore": 0, "iterations_since_restore": 17}
{"mean_reward": -117.73149425556738, "trial_id": "ee86f856", "training_iteration": 17, "time_this_iter_s": 1047.655793428421, "done": false, "timesteps_total": null, "episodes_total": null, "experiment_id": "6b5c107e285b4c09bc642e2787508c14", "date": "2019-11-16_04-41-28", "timestamp": 1573879288, "time_total_s": 17857.042757987976, "pid": 13777, "hostname": "213cedb5f1ad", "node_ip": "172.18.0.3", "config": {"replay_size": 10000, "lr": 0.001, "batch_size": 32, "refresh_target_network_freq": 2000, "opt_steps_per_step": 2}, "time_since_restore": 17857.042757987976, "timesteps_since_restore": 0, "iterations_since_restore": 18}
{"mean_reward": -105.61189955886816, "trial_id": "ee86f856", "training_iteration": 18, "time_this_iter_s": 1052.5095291137695, "done": false, "timesteps_total": null, "episodes_total": null, "experiment_id": "6b5c107e285b4c09bc642e2787508c14", "date": "2019-11-16_04-59-00", "timestamp": 1573880340, "time_total_s": 18909.552287101746, "pid": 13777, "hostname": "213cedb5f1ad", "node_ip": "172.18.0.3", "config": {"replay_size": 10000, "lr": 0.001, "batch_size": 32, "refresh_target_network_freq": 2000, "opt_steps_per_step": 2}, "time_since_restore": 18909.552287101746, "timesteps_since_restore": 0, "iterations_since_restore": 19}
{"mean_reward": -103.47514796910276, "trial_id": "ee86f856", "training_iteration": 19, "time_this_iter_s": 1063.2427825927734, "done": false, "timesteps_total": null, "episodes_total": null, "experiment_id": "6b5c107e285b4c09bc642e2787508c14", "date": "2019-11-16_05-16-43", "timestamp": 1573881403, "time_total_s": 19972.79506969452, "pid": 13777, "hostname": "213cedb5f1ad", "node_ip": "172.18.0.3", "config": {"replay_size": 10000, "lr": 0.001, "batch_size": 32, "refresh_target_network_freq": 2000, "opt_steps_per_step": 2}, "time_since_restore": 19972.79506969452, "timesteps_since_restore": 0, "iterations_since_restore": 20}
{"mean_reward": -102.22715735174332, "trial_id": "ee86f856", "training_iteration": 20, "time_this_iter_s": 1019.6744494438171, "done": false, "timesteps_total": null, "episodes_total": null, "experiment_id": "6b5c107e285b4c09bc642e2787508c14", "date": "2019-11-16_05-33-43", "timestamp": 1573882423, "time_total_s": 20992.469519138336, "pid": 13777, "hostname": "213cedb5f1ad", "node_ip": "172.18.0.3", "config": {"replay_size": 10000, "lr": 0.001, "batch_size": 32, "refresh_target_network_freq": 2000, "opt_steps_per_step": 2}, "time_since_restore": 20992.469519138336, "timesteps_since_restore": 0, "iterations_since_restore": 21}
{"mean_reward": -91.25628946230604, "trial_id": "ee86f856", "training_iteration": 21, "time_this_iter_s": 1063.823444366455, "done": false, "timesteps_total": null, "episodes_total": null, "experiment_id": "6b5c107e285b4c09bc642e2787508c14", "date": "2019-11-16_05-51-27", "timestamp": 1573883487, "time_total_s": 22056.29296350479, "pid": 13777, "hostname": "213cedb5f1ad", "node_ip": "172.18.0.3", "config": {"replay_size": 10000, "lr": 0.001, "batch_size": 32, "refresh_target_network_freq": 2000, "opt_steps_per_step": 2}, "time_since_restore": 22056.29296350479, "timesteps_since_restore": 0, "iterations_since_restore": 22}
{"mean_reward": -113.73463131397675, "trial_id": "ee86f856", "training_iteration": 22, "time_this_iter_s": 1061.687673330307, "done": false, "timesteps_total": null, "episodes_total": null, "experiment_id": "6b5c107e285b4c09bc642e2787508c14", "date": "2019-11-16_06-09-09", "timestamp": 1573884549, "time_total_s": 23117.9806368351, "pid": 13777, "hostname": "213cedb5f1ad", "node_ip": "172.18.0.3", "config": {"replay_size": 10000, "lr": 0.001, "batch_size": 32, "refresh_target_network_freq": 2000, "opt_steps_per_step": 2}, "time_since_restore": 23117.9806368351, "timesteps_since_restore": 0, "iterations_since_restore": 23}
{"mean_reward": -117.11774023435682, "trial_id": "ee86f856", "training_iteration": 23, "time_this_iter_s": 1076.2460100650787, "done": false, "timesteps_total": null, "episodes_total": null, "experiment_id": "6b5c107e285b4c09bc642e2787508c14", "date": "2019-11-16_06-27-05", "timestamp": 1573885625, "time_total_s": 24194.226646900177, "pid": 13777, "hostname": "213cedb5f1ad", "node_ip": "172.18.0.3", "config": {"replay_size": 10000, "lr": 0.001, "batch_size": 32, "refresh_target_network_freq": 2000, "opt_steps_per_step": 2}, "time_since_restore": 24194.226646900177, "timesteps_since_restore": 0, "iterations_since_restore": 24}
{"mean_reward": -108.44409600663829, "trial_id": "ee86f856", "training_iteration": 24, "time_this_iter_s": 1068.407381772995, "done": false, "timesteps_total": null, "episodes_total": null, "experiment_id": "6b5c107e285b4c09bc642e2787508c14", "date": "2019-11-16_06-44-53", "timestamp": 1573886693, "time_total_s": 25262.634028673172, "pid": 13777, "hostname": "213cedb5f1ad", "node_ip": "172.18.0.3", "config": {"replay_size": 10000, "lr": 0.001, "batch_size": 32, "refresh_target_network_freq": 2000, "opt_steps_per_step": 2}, "time_since_restore": 25262.634028673172, "timesteps_since_restore": 0, "iterations_since_restore": 25}
{"mean_reward": -24.560373688791984, "trial_id": "ee86f856", "training_iteration": 25, "time_this_iter_s": 1068.9893686771393, "done": false, "timesteps_total": null, "episodes_total": null, "experiment_id": "6b5c107e285b4c09bc642e2787508c14", "date": "2019-11-16_07-02-42", "timestamp": 1573887762, "time_total_s": 26331.62339735031, "pid": 13777, "hostname": "213cedb5f1ad", "node_ip": "172.18.0.3", "config": {"replay_size": 10000, "lr": 0.001, "batch_size": 32, "refresh_target_network_freq": 2000, "opt_steps_per_step": 2}, "time_since_restore": 26331.62339735031, "timesteps_since_restore": 0, "iterations_since_restore": 26}
{"mean_reward": -88.74335635518507, "trial_id": "ee86f856", "training_iteration": 26, "time_this_iter_s": 1077.8767211437225, "done": false, "timesteps_total": null, "episodes_total": null, "experiment_id": "6b5c107e285b4c09bc642e2787508c14", "date": "2019-11-16_07-20-40", "timestamp": 1573888840, "time_total_s": 27409.500118494034, "pid": 13777, "hostname": "213cedb5f1ad", "node_ip": "172.18.0.3", "config": {"replay_size": 10000, "lr": 0.001, "batch_size": 32, "refresh_target_network_freq": 2000, "opt_steps_per_step": 2}, "time_since_restore": 27409.500118494034, "timesteps_since_restore": 0, "iterations_since_restore": 27}
{"mean_reward": -108.30440737797305, "trial_id": "ee86f856", "training_iteration": 27, "time_this_iter_s": 1082.4064013957977, "done": false, "timesteps_total": null, "episodes_total": null, "experiment_id": "6b5c107e285b4c09bc642e2787508c14", "date": "2019-11-16_07-38-43", "timestamp": 1573889923, "time_total_s": 28491.90651988983, "pid": 13777, "hostname": "213cedb5f1ad", "node_ip": "172.18.0.3", "config": {"replay_size": 10000, "lr": 0.001, "batch_size": 32, "refresh_target_network_freq": 2000, "opt_steps_per_step": 2}, "time_since_restore": 28491.90651988983, "timesteps_since_restore": 0, "iterations_since_restore": 28}
{"mean_reward": -113.0105083183106, "trial_id": "ee86f856", "training_iteration": 28, "time_this_iter_s": 1046.8332715034485, "done": false, "timesteps_total": null, "episodes_total": null, "experiment_id": "6b5c107e285b4c09bc642e2787508c14", "date": "2019-11-16_07-56-09", "timestamp": 1573890969, "time_total_s": 29538.73979139328, "pid": 13777, "hostname": "213cedb5f1ad", "node_ip": "172.18.0.3", "config": {"replay_size": 10000, "lr": 0.001, "batch_size": 32, "refresh_target_network_freq": 2000, "opt_steps_per_step": 2}, "time_since_restore": 29538.73979139328, "timesteps_since_restore": 0, "iterations_since_restore": 29}
{"mean_reward": -92.74799032962765, "trial_id": "ee86f856", "training_iteration": 29, "time_this_iter_s": 1041.4210796356201, "done": false, "timesteps_total": null, "episodes_total": null, "experiment_id": "6b5c107e285b4c09bc642e2787508c14", "date": "2019-11-16_08-13-31", "timestamp": 1573892011, "time_total_s": 30580.1608710289, "pid": 13777, "hostname": "213cedb5f1ad", "node_ip": "172.18.0.3", "config": {"replay_size": 10000, "lr": 0.001, "batch_size": 32, "refresh_target_network_freq": 2000, "opt_steps_per_step": 2}, "time_since_restore": 30580.1608710289, "timesteps_since_restore": 0, "iterations_since_restore": 30}
{"mean_reward": -125.68213220343529, "trial_id": "ee86f856", "training_iteration": 30, "time_this_iter_s": 1068.9413142204285, "done": false, "timesteps_total": null, "episodes_total": null, "experiment_id": "6b5c107e285b4c09bc642e2787508c14", "date": "2019-11-16_08-31-20", "timestamp": 1573893080, "time_total_s": 31649.10218524933, "pid": 13777, "hostname": "213cedb5f1ad", "node_ip": "172.18.0.3", "config": {"replay_size": 10000, "lr": 0.001, "batch_size": 32, "refresh_target_network_freq": 2000, "opt_steps_per_step": 2}, "time_since_restore": 31649.10218524933, "timesteps_since_restore": 0, "iterations_since_restore": 31}
{"mean_reward": -105.15408466314851, "trial_id": "ee86f856", "training_iteration": 31, "time_this_iter_s": 1053.5503675937653, "done": false, "timesteps_total": null, "episodes_total": null, "experiment_id": "6b5c107e285b4c09bc642e2787508c14", "date": "2019-11-16_08-48-53", "timestamp": 1573894133, "time_total_s": 32702.652552843094, "pid": 13777, "hostname": "213cedb5f1ad", "node_ip": "172.18.0.3", "config": {"replay_size": 10000, "lr": 0.001, "batch_size": 32, "refresh_target_network_freq": 2000, "opt_steps_per_step": 2}, "time_since_restore": 32702.652552843094, "timesteps_since_restore": 0, "iterations_since_restore": 32}
{"mean_reward": -139.51116671556355, "trial_id": "ee86f856", "training_iteration": 32, "time_this_iter_s": 1071.1854765415192, "done": false, "timesteps_total": null, "episodes_total": null, "experiment_id": "6b5c107e285b4c09bc642e2787508c14", "date": "2019-11-16_09-06-44", "timestamp": 1573895204, "time_total_s": 33773.83802938461, "pid": 13777, "hostname": "213cedb5f1ad", "node_ip": "172.18.0.3", "config": {"replay_size": 10000, "lr": 0.001, "batch_size": 32, "refresh_target_network_freq": 2000, "opt_steps_per_step": 2}, "time_since_restore": 33773.83802938461, "timesteps_since_restore": 0, "iterations_since_restore": 33}
{"mean_reward": -114.65010419012913, "trial_id": "ee86f856", "training_iteration": 33, "time_this_iter_s": 1019.4702477455139, "done": false, "timesteps_total": null, "episodes_total": null, "experiment_id": "6b5c107e285b4c09bc642e2787508c14", "date": "2019-11-16_09-23-44", "timestamp": 1573896224, "time_total_s": 34793.30827713013, "pid": 13777, "hostname": "213cedb5f1ad", "node_ip": "172.18.0.3", "config": {"replay_size": 10000, "lr": 0.001, "batch_size": 32, "refresh_target_network_freq": 2000, "opt_steps_per_step": 2}, "time_since_restore": 34793.30827713013, "timesteps_since_restore": 0, "iterations_since_restore": 34}
{"mean_reward": -108.84579193331052, "trial_id": "ee86f856", "training_iteration": 34, "time_this_iter_s": 1032.2634167671204, "done": false, "timesteps_total": null, "episodes_total": null, "experiment_id": "6b5c107e285b4c09bc642e2787508c14", "date": "2019-11-16_09-40-56", "timestamp": 1573897256, "time_total_s": 35825.57169389725, "pid": 13777, "hostname": "213cedb5f1ad", "node_ip": "172.18.0.3", "config": {"replay_size": 10000, "lr": 0.001, "batch_size": 32, "refresh_target_network_freq": 2000, "opt_steps_per_step": 2}, "time_since_restore": 35825.57169389725, "timesteps_since_restore": 0, "iterations_since_restore": 35}
{"mean_reward": -155.46937396439338, "trial_id": "ee86f856", "training_iteration": 35, "time_this_iter_s": 1037.10742020607, "done": false, "timesteps_total": null, "episodes_total": null, "experiment_id": "6b5c107e285b4c09bc642e2787508c14", "date": "2019-11-16_09-58-13", "timestamp": 1573898293, "time_total_s": 36862.67911410332, "pid": 13777, "hostname": "213cedb5f1ad", "node_ip": "172.18.0.3", "config": {"replay_size": 10000, "lr": 0.001, "batch_size": 32, "refresh_target_network_freq": 2000, "opt_steps_per_step": 2}, "time_since_restore": 36862.67911410332, "timesteps_since_restore": 0, "iterations_since_restore": 36}
{"mean_reward": -107.74769660011884, "trial_id": "ee86f856", "training_iteration": 36, "time_this_iter_s": 1046.7872223854065, "done": false, "timesteps_total": null, "episodes_total": null, "experiment_id": "6b5c107e285b4c09bc642e2787508c14", "date": "2019-11-16_10-15-40", "timestamp": 1573899340, "time_total_s": 37909.466336488724, "pid": 13777, "hostname": "213cedb5f1ad", "node_ip": "172.18.0.3", "config": {"replay_size": 10000, "lr": 0.001, "batch_size": 32, "refresh_target_network_freq": 2000, "opt_steps_per_step": 2}, "time_since_restore": 37909.466336488724, "timesteps_since_restore": 0, "iterations_since_restore": 37}
{"mean_reward": -129.15043352747853, "trial_id": "ee86f856", "training_iteration": 37, "time_this_iter_s": 1019.4986157417297, "done": false, "timesteps_total": null, "episodes_total": null, "experiment_id": "6b5c107e285b4c09bc642e2787508c14", "date": "2019-11-16_10-32-40", "timestamp": 1573900360, "time_total_s": 38928.96495223045, "pid": 13777, "hostname": "213cedb5f1ad", "node_ip": "172.18.0.3", "config": {"replay_size": 10000, "lr": 0.001, "batch_size": 32, "refresh_target_network_freq": 2000, "opt_steps_per_step": 2}, "time_since_restore": 38928.96495223045, "timesteps_since_restore": 0, "iterations_since_restore": 38}
{"mean_reward": -104.9274341996989, "trial_id": "ee86f856", "training_iteration": 38, "time_this_iter_s": 1016.8207149505615, "done": false, "timesteps_total": null, "episodes_total": null, "experiment_id": "6b5c107e285b4c09bc642e2787508c14", "date": "2019-11-16_10-49-36", "timestamp": 1573901376, "time_total_s": 39945.785667181015, "pid": 13777, "hostname": "213cedb5f1ad", "node_ip": "172.18.0.3", "config": {"replay_size": 10000, "lr": 0.001, "batch_size": 32, "refresh_target_network_freq": 2000, "opt_steps_per_step": 2}, "time_since_restore": 39945.785667181015, "timesteps_since_restore": 0, "iterations_since_restore": 39}
{"mean_reward": -116.67900175050245, "trial_id": "ee86f856", "training_iteration": 39, "time_this_iter_s": 1067.050584077835, "done": false, "timesteps_total": null, "episodes_total": null, "experiment_id": "6b5c107e285b4c09bc642e2787508c14", "date": "2019-11-16_11-07-23", "timestamp": 1573902443, "time_total_s": 41012.83625125885, "pid": 13777, "hostname": "213cedb5f1ad", "node_ip": "172.18.0.3", "config": {"replay_size": 10000, "lr": 0.001, "batch_size": 32, "refresh_target_network_freq": 2000, "opt_steps_per_step": 2}, "time_since_restore": 41012.83625125885, "timesteps_since_restore": 0, "iterations_since_restore": 40}
{"mean_reward": -111.77361046743516, "trial_id": "ee86f856", "training_iteration": 40, "time_this_iter_s": 1050.9391722679138, "done": false, "timesteps_total": null, "episodes_total": null, "experiment_id": "6b5c107e285b4c09bc642e2787508c14", "date": "2019-11-16_11-24-54", "timestamp": 1573903494, "time_total_s": 42063.775423526764, "pid": 13777, "hostname": "213cedb5f1ad", "node_ip": "172.18.0.3", "config": {"replay_size": 10000, "lr": 0.001, "batch_size": 32, "refresh_target_network_freq": 2000, "opt_steps_per_step": 2}, "time_since_restore": 42063.775423526764, "timesteps_since_restore": 0, "iterations_since_restore": 41}
{"mean_reward": -102.26779491496758, "trial_id": "ee86f856", "training_iteration": 41, "time_this_iter_s": 1018.0842504501343, "done": false, "timesteps_total": null, "episodes_total": null, "experiment_id": "6b5c107e285b4c09bc642e2787508c14", "date": "2019-11-16_11-41-52", "timestamp": 1573904512, "time_total_s": 43081.8596739769, "pid": 13777, "hostname": "213cedb5f1ad", "node_ip": "172.18.0.3", "config": {"replay_size": 10000, "lr": 0.001, "batch_size": 32, "refresh_target_network_freq": 2000, "opt_steps_per_step": 2}, "time_since_restore": 43081.8596739769, "timesteps_since_restore": 0, "iterations_since_restore": 42}
{"mean_reward": -95.73591291444711, "trial_id": "ee86f856", "training_iteration": 42, "time_this_iter_s": 1041.3302836418152, "done": false, "timesteps_total": null, "episodes_total": null, "experiment_id": "6b5c107e285b4c09bc642e2787508c14", "date": "2019-11-16_11-59-14", "timestamp": 1573905554, "time_total_s": 44123.18995761871, "pid": 13777, "hostname": "213cedb5f1ad", "node_ip": "172.18.0.3", "config": {"replay_size": 10000, "lr": 0.001, "batch_size": 32, "refresh_target_network_freq": 2000, "opt_steps_per_step": 2}, "time_since_restore": 44123.18995761871, "timesteps_since_restore": 0, "iterations_since_restore": 43}
{"mean_reward": -110.34942527089972, "trial_id": "ee86f856", "training_iteration": 43, "time_this_iter_s": 1023.3171856403351, "done": false, "timesteps_total": null, "episodes_total": null, "experiment_id": "6b5c107e285b4c09bc642e2787508c14", "date": "2019-11-16_12-16-17", "timestamp": 1573906577, "time_total_s": 45146.50714325905, "pid": 13777, "hostname": "213cedb5f1ad", "node_ip": "172.18.0.3", "config": {"replay_size": 10000, "lr": 0.001, "batch_size": 32, "refresh_target_network_freq": 2000, "opt_steps_per_step": 2}, "time_since_restore": 45146.50714325905, "timesteps_since_restore": 0, "iterations_since_restore": 44}
{"mean_reward": -104.35798858556909, "trial_id": "ee86f856", "training_iteration": 44, "time_this_iter_s": 1047.8270001411438, "done": false, "timesteps_total": null, "episodes_total": null, "experiment_id": "6b5c107e285b4c09bc642e2787508c14", "date": "2019-11-16_12-33-45", "timestamp": 1573907625, "time_total_s": 46194.33414340019, "pid": 13777, "hostname": "213cedb5f1ad", "node_ip": "172.18.0.3", "config": {"replay_size": 10000, "lr": 0.001, "batch_size": 32, "refresh_target_network_freq": 2000, "opt_steps_per_step": 2}, "time_since_restore": 46194.33414340019, "timesteps_since_restore": 0, "iterations_since_restore": 45}
{"mean_reward": -94.49955095150285, "trial_id": "ee86f856", "training_iteration": 45, "time_this_iter_s": 1029.9641606807709, "done": false, "timesteps_total": null, "episodes_total": null, "experiment_id": "6b5c107e285b4c09bc642e2787508c14", "date": "2019-11-16_12-50-55", "timestamp": 1573908655, "time_total_s": 47224.29830408096, "pid": 13777, "hostname": "213cedb5f1ad", "node_ip": "172.18.0.3", "config": {"replay_size": 10000, "lr": 0.001, "batch_size": 32, "refresh_target_network_freq": 2000, "opt_steps_per_step": 2}, "time_since_restore": 47224.29830408096, "timesteps_since_restore": 0, "iterations_since_restore": 46}
{"mean_reward": -117.84052171783149, "trial_id": "ee86f856", "training_iteration": 46, "time_this_iter_s": 990.3387973308563, "done": false, "timesteps_total": null, "episodes_total": null, "experiment_id": "6b5c107e285b4c09bc642e2787508c14", "date": "2019-11-16_13-07-25", "timestamp": 1573909645, "time_total_s": 48214.63710141182, "pid": 13777, "hostname": "213cedb5f1ad", "node_ip": "172.18.0.3", "config": {"replay_size": 10000, "lr": 0.001, "batch_size": 32, "refresh_target_network_freq": 2000, "opt_steps_per_step": 2}, "time_since_restore": 48214.63710141182, "timesteps_since_restore": 0, "iterations_since_restore": 47}
{"mean_reward": -103.93084614794816, "trial_id": "ee86f856", "training_iteration": 47, "time_this_iter_s": 1006.2430555820465, "done": false, "timesteps_total": null, "episodes_total": null, "experiment_id": "6b5c107e285b4c09bc642e2787508c14", "date": "2019-11-16_13-24-12", "timestamp": 1573910652, "time_total_s": 49220.880156993866, "pid": 13777, "hostname": "213cedb5f1ad", "node_ip": "172.18.0.3", "config": {"replay_size": 10000, "lr": 0.001, "batch_size": 32, "refresh_target_network_freq": 2000, "opt_steps_per_step": 2}, "time_since_restore": 49220.880156993866, "timesteps_since_restore": 0, "iterations_since_restore": 48}
{"mean_reward": -55.86419138460628, "trial_id": "ee86f856", "training_iteration": 48, "time_this_iter_s": 1012.3217763900757, "done": false, "timesteps_total": null, "episodes_total": null, "experiment_id": "6b5c107e285b4c09bc642e2787508c14", "date": "2019-11-16_13-41-04", "timestamp": 1573911664, "time_total_s": 50233.20193338394, "pid": 13777, "hostname": "213cedb5f1ad", "node_ip": "172.18.0.3", "config": {"replay_size": 10000, "lr": 0.001, "batch_size": 32, "refresh_target_network_freq": 2000, "opt_steps_per_step": 2}, "time_since_restore": 50233.20193338394, "timesteps_since_restore": 0, "iterations_since_restore": 49}
{"mean_reward": -65.14347003087066, "trial_id": "ee86f856", "training_iteration": 49, "time_this_iter_s": 968.6804413795471, "done": false, "timesteps_total": null, "episodes_total": null, "experiment_id": "6b5c107e285b4c09bc642e2787508c14", "date": "2019-11-16_13-57-13", "timestamp": 1573912633, "time_total_s": 51201.88237476349, "pid": 13777, "hostname": "213cedb5f1ad", "node_ip": "172.18.0.3", "config": {"replay_size": 10000, "lr": 0.001, "batch_size": 32, "refresh_target_network_freq": 2000, "opt_steps_per_step": 2}, "time_since_restore": 51201.88237476349, "timesteps_since_restore": 0, "iterations_since_restore": 50}
{"mean_reward": -39.46430029046276, "trial_id": "ee86f856", "training_iteration": 50, "time_this_iter_s": 977.1627221107483, "done": false, "timesteps_total": null, "episodes_total": null, "experiment_id": "6b5c107e285b4c09bc642e2787508c14", "date": "2019-11-16_14-13-30", "timestamp": 1573913610, "time_total_s": 52179.04509687424, "pid": 13777, "hostname": "213cedb5f1ad", "node_ip": "172.18.0.3", "config": {"replay_size": 10000, "lr": 0.001, "batch_size": 32, "refresh_target_network_freq": 2000, "opt_steps_per_step": 2}, "time_since_restore": 52179.04509687424, "timesteps_since_restore": 0, "iterations_since_restore": 51}
{"mean_reward": -46.323348393492324, "trial_id": "ee86f856", "training_iteration": 51, "time_this_iter_s": 980.7633800506592, "done": false, "timesteps_total": null, "episodes_total": null, "experiment_id": "6b5c107e285b4c09bc642e2787508c14", "date": "2019-11-16_14-29-50", "timestamp": 1573914590, "time_total_s": 53159.808476924896, "pid": 13777, "hostname": "213cedb5f1ad", "node_ip": "172.18.0.3", "config": {"replay_size": 10000, "lr": 0.001, "batch_size": 32, "refresh_target_network_freq": 2000, "opt_steps_per_step": 2}, "time_since_restore": 53159.808476924896, "timesteps_since_restore": 0, "iterations_since_restore": 52}
{"mean_reward": -126.52296119111467, "trial_id": "ee86f856", "training_iteration": 52, "time_this_iter_s": 957.2230997085571, "done": false, "timesteps_total": null, "episodes_total": null, "experiment_id": "6b5c107e285b4c09bc642e2787508c14", "date": "2019-11-16_14-45-48", "timestamp": 1573915548, "time_total_s": 54117.03157663345, "pid": 13777, "hostname": "213cedb5f1ad", "node_ip": "172.18.0.3", "config": {"replay_size": 10000, "lr": 0.001, "batch_size": 32, "refresh_target_network_freq": 2000, "opt_steps_per_step": 2}, "time_since_restore": 54117.03157663345, "timesteps_since_restore": 0, "iterations_since_restore": 53}
{"mean_reward": -117.03570775981655, "trial_id": "ee86f856", "training_iteration": 53, "time_this_iter_s": 972.4729351997375, "done": false, "timesteps_total": null, "episodes_total": null, "experiment_id": "6b5c107e285b4c09bc642e2787508c14", "date": "2019-11-16_15-02-00", "timestamp": 1573916520, "time_total_s": 55089.50451183319, "pid": 13777, "hostname": "213cedb5f1ad", "node_ip": "172.18.0.3", "config": {"replay_size": 10000, "lr": 0.001, "batch_size": 32, "refresh_target_network_freq": 2000, "opt_steps_per_step": 2}, "time_since_restore": 55089.50451183319, "timesteps_since_restore": 0, "iterations_since_restore": 54}
{"mean_reward": -82.211325552618, "trial_id": "ee86f856", "training_iteration": 54, "time_this_iter_s": 970.537816286087, "done": false, "timesteps_total": null, "episodes_total": null, "experiment_id": "6b5c107e285b4c09bc642e2787508c14", "date": "2019-11-16_15-18-11", "timestamp": 1573917491, "time_total_s": 56060.04232811928, "pid": 13777, "hostname": "213cedb5f1ad", "node_ip": "172.18.0.3", "config": {"replay_size": 10000, "lr": 0.001, "batch_size": 32, "refresh_target_network_freq": 2000, "opt_steps_per_step": 2}, "time_since_restore": 56060.04232811928, "timesteps_since_restore": 0, "iterations_since_restore": 55}
{"mean_reward": -108.89138470713372, "trial_id": "ee86f856", "training_iteration": 55, "time_this_iter_s": 974.5284860134125, "done": false, "timesteps_total": null, "episodes_total": null, "experiment_id": "6b5c107e285b4c09bc642e2787508c14", "date": "2019-11-16_15-34-25", "timestamp": 1573918465, "time_total_s": 57034.57081413269, "pid": 13777, "hostname": "213cedb5f1ad", "node_ip": "172.18.0.3", "config": {"replay_size": 10000, "lr": 0.001, "batch_size": 32, "refresh_target_network_freq": 2000, "opt_steps_per_step": 2}, "time_since_restore": 57034.57081413269, "timesteps_since_restore": 0, "iterations_since_restore": 56}
{"mean_reward": -125.67726398909849, "trial_id": "ee86f856", "training_iteration": 56, "time_this_iter_s": 965.699383020401, "done": false, "timesteps_total": null, "episodes_total": null, "experiment_id": "6b5c107e285b4c09bc642e2787508c14", "date": "2019-11-16_15-50-31", "timestamp": 1573919431, "time_total_s": 58000.27019715309, "pid": 13777, "hostname": "213cedb5f1ad", "node_ip": "172.18.0.3", "config": {"replay_size": 10000, "lr": 0.001, "batch_size": 32, "refresh_target_network_freq": 2000, "opt_steps_per_step": 2}, "time_since_restore": 58000.27019715309, "timesteps_since_restore": 0, "iterations_since_restore": 57}
{"mean_reward": -134.98304626282183, "trial_id": "ee86f856", "training_iteration": 57, "time_this_iter_s": 970.788236618042, "done": false, "timesteps_total": null, "episodes_total": null, "experiment_id": "6b5c107e285b4c09bc642e2787508c14", "date": "2019-11-16_16-06-42", "timestamp": 1573920402, "time_total_s": 58971.05843377113, "pid": 13777, "hostname": "213cedb5f1ad", "node_ip": "172.18.0.3", "config": {"replay_size": 10000, "lr": 0.001, "batch_size": 32, "refresh_target_network_freq": 2000, "opt_steps_per_step": 2}, "time_since_restore": 58971.05843377113, "timesteps_since_restore": 0, "iterations_since_restore": 58}
{"mean_reward": 3.0814425989377447, "trial_id": "ee86f856", "training_iteration": 58, "time_this_iter_s": 970.2968809604645, "done": false, "timesteps_total": null, "episodes_total": null, "experiment_id": "6b5c107e285b4c09bc642e2787508c14", "date": "2019-11-16_16-22-52", "timestamp": 1573921372, "time_total_s": 59941.3553147316, "pid": 13777, "hostname": "213cedb5f1ad", "node_ip": "172.18.0.3", "config": {"replay_size": 10000, "lr": 0.001, "batch_size": 32, "refresh_target_network_freq": 2000, "opt_steps_per_step": 2}, "time_since_restore": 59941.3553147316, "timesteps_since_restore": 0, "iterations_since_restore": 59}
{"mean_reward": 14.72374210895934, "trial_id": "ee86f856", "training_iteration": 59, "time_this_iter_s": 968.0742540359497, "done": false, "timesteps_total": null, "episodes_total": null, "experiment_id": "6b5c107e285b4c09bc642e2787508c14", "date": "2019-11-16_16-39-00", "timestamp": 1573922340, "time_total_s": 60909.42956876755, "pid": 13777, "hostname": "213cedb5f1ad", "node_ip": "172.18.0.3", "config": {"replay_size": 10000, "lr": 0.001, "batch_size": 32, "refresh_target_network_freq": 2000, "opt_steps_per_step": 2}, "time_since_restore": 60909.42956876755, "timesteps_since_restore": 0, "iterations_since_restore": 60}
{"mean_reward": -63.6758147410205, "trial_id": "ee86f856", "training_iteration": 60, "time_this_iter_s": 938.9915134906769, "done": false, "timesteps_total": null, "episodes_total": null, "experiment_id": "6b5c107e285b4c09bc642e2787508c14", "date": "2019-11-16_16-54-39", "timestamp": 1573923279, "time_total_s": 61848.421082258224, "pid": 13777, "hostname": "213cedb5f1ad", "node_ip": "172.18.0.3", "config": {"replay_size": 10000, "lr": 0.001, "batch_size": 32, "refresh_target_network_freq": 2000, "opt_steps_per_step": 2}, "time_since_restore": 61848.421082258224, "timesteps_since_restore": 0, "iterations_since_restore": 61}
