{"mean_reward": -109.65203356324947, "trial_id": "ee8064fa", "training_iteration": 0, "time_this_iter_s": 34.9432430267334, "done": false, "timesteps_total": null, "episodes_total": null, "experiment_id": "ae7a5e6bac20431bb594eb8184b72316", "date": "2019-11-15_09-26-40", "timestamp": 1573810000, "time_total_s": 34.9432430267334, "pid": 270, "hostname": "213cedb5f1ad", "node_ip": "172.18.0.3", "config": {"replay_size": 10000, "lr": 0.0001, "batch_size": 16, "refresh_target_network_freq": 3000, "opt_steps_per_step": 2}, "time_since_restore": 34.9432430267334, "timesteps_since_restore": 0, "iterations_since_restore": 1}
{"mean_reward": -108.80044494673423, "trial_id": "ee8064fa", "training_iteration": 1, "time_this_iter_s": 545.3695166110992, "done": false, "timesteps_total": null, "episodes_total": null, "experiment_id": "ae7a5e6bac20431bb594eb8184b72316", "date": "2019-11-15_09-35-45", "timestamp": 1573810545, "time_total_s": 580.3127596378326, "pid": 270, "hostname": "213cedb5f1ad", "node_ip": "172.18.0.3", "config": {"replay_size": 10000, "lr": 0.0001, "batch_size": 16, "refresh_target_network_freq": 3000, "opt_steps_per_step": 2}, "time_since_restore": 580.3127596378326, "timesteps_since_restore": 0, "iterations_since_restore": 2}
{"mean_reward": -52.34327953468488, "trial_id": "ee8064fa", "training_iteration": 2, "time_this_iter_s": 602.3361797332764, "done": false, "timesteps_total": null, "episodes_total": null, "experiment_id": "ae7a5e6bac20431bb594eb8184b72316", "date": "2019-11-15_09-45-48", "timestamp": 1573811148, "time_total_s": 1182.648939371109, "pid": 270, "hostname": "213cedb5f1ad", "node_ip": "172.18.0.3", "config": {"replay_size": 10000, "lr": 0.0001, "batch_size": 16, "refresh_target_network_freq": 3000, "opt_steps_per_step": 2}, "time_since_restore": 1182.648939371109, "timesteps_since_restore": 0, "iterations_since_restore": 3}
{"mean_reward": -106.54251227799296, "trial_id": "ee8064fa", "training_iteration": 3, "time_this_iter_s": 553.757387638092, "done": false, "timesteps_total": null, "episodes_total": null, "experiment_id": "ae7a5e6bac20431bb594eb8184b72316", "date": "2019-11-15_09-55-01", "timestamp": 1573811701, "time_total_s": 1736.406327009201, "pid": 270, "hostname": "213cedb5f1ad", "node_ip": "172.18.0.3", "config": {"replay_size": 10000, "lr": 0.0001, "batch_size": 16, "refresh_target_network_freq": 3000, "opt_steps_per_step": 2}, "time_since_restore": 1736.406327009201, "timesteps_since_restore": 0, "iterations_since_restore": 4}
{"mean_reward": -100.23236747570513, "trial_id": "ee8064fa", "training_iteration": 4, "time_this_iter_s": 563.81654047966, "done": false, "timesteps_total": null, "episodes_total": null, "experiment_id": "ae7a5e6bac20431bb594eb8184b72316", "date": "2019-11-15_10-04-25", "timestamp": 1573812265, "time_total_s": 2300.222867488861, "pid": 270, "hostname": "213cedb5f1ad", "node_ip": "172.18.0.3", "config": {"replay_size": 10000, "lr": 0.0001, "batch_size": 16, "refresh_target_network_freq": 3000, "opt_steps_per_step": 2}, "time_since_restore": 2300.222867488861, "timesteps_since_restore": 0, "iterations_since_restore": 5}
{"mean_reward": -103.00125012070066, "trial_id": "ee8064fa", "training_iteration": 5, "time_this_iter_s": 565.9238398075104, "done": false, "timesteps_total": null, "episodes_total": null, "experiment_id": "ae7a5e6bac20431bb594eb8184b72316", "date": "2019-11-15_10-13-51", "timestamp": 1573812831, "time_total_s": 2866.1467072963715, "pid": 270, "hostname": "213cedb5f1ad", "node_ip": "172.18.0.3", "config": {"replay_size": 10000, "lr": 0.0001, "batch_size": 16, "refresh_target_network_freq": 3000, "opt_steps_per_step": 2}, "time_since_restore": 2866.1467072963715, "timesteps_since_restore": 0, "iterations_since_restore": 6}
{"mean_reward": -87.78536367864945, "trial_id": "ee8064fa", "training_iteration": 6, "time_this_iter_s": 561.9031202793121, "done": false, "timesteps_total": null, "episodes_total": null, "experiment_id": "ae7a5e6bac20431bb594eb8184b72316", "date": "2019-11-15_10-23-13", "timestamp": 1573813393, "time_total_s": 3428.0498275756836, "pid": 270, "hostname": "213cedb5f1ad", "node_ip": "172.18.0.3", "config": {"replay_size": 10000, "lr": 0.0001, "batch_size": 16, "refresh_target_network_freq": 3000, "opt_steps_per_step": 2}, "time_since_restore": 3428.0498275756836, "timesteps_since_restore": 0, "iterations_since_restore": 7}
{"mean_reward": -100.49083766373701, "trial_id": "ee8064fa", "training_iteration": 7, "time_this_iter_s": 553.0784392356873, "done": false, "timesteps_total": null, "episodes_total": null, "experiment_id": "ae7a5e6bac20431bb594eb8184b72316", "date": "2019-11-15_10-32-26", "timestamp": 1573813946, "time_total_s": 3981.128266811371, "pid": 270, "hostname": "213cedb5f1ad", "node_ip": "172.18.0.3", "config": {"replay_size": 10000, "lr": 0.0001, "batch_size": 16, "refresh_target_network_freq": 3000, "opt_steps_per_step": 2}, "time_since_restore": 3981.128266811371, "timesteps_since_restore": 0, "iterations_since_restore": 8}
{"mean_reward": -109.77580128397096, "trial_id": "ee8064fa", "training_iteration": 8, "time_this_iter_s": 580.5886406898499, "done": false, "timesteps_total": null, "episodes_total": null, "experiment_id": "ae7a5e6bac20431bb594eb8184b72316", "date": "2019-11-15_10-42-07", "timestamp": 1573814527, "time_total_s": 4561.716907501221, "pid": 270, "hostname": "213cedb5f1ad", "node_ip": "172.18.0.3", "config": {"replay_size": 10000, "lr": 0.0001, "batch_size": 16, "refresh_target_network_freq": 3000, "opt_steps_per_step": 2}, "time_since_restore": 4561.716907501221, "timesteps_since_restore": 0, "iterations_since_restore": 9}
{"mean_reward": -107.24580239324769, "trial_id": "ee8064fa", "training_iteration": 9, "time_this_iter_s": 564.0828940868378, "done": false, "timesteps_total": null, "episodes_total": null, "experiment_id": "ae7a5e6bac20431bb594eb8184b72316", "date": "2019-11-15_10-51-31", "timestamp": 1573815091, "time_total_s": 5125.7998015880585, "pid": 270, "hostname": "213cedb5f1ad", "node_ip": "172.18.0.3", "config": {"replay_size": 10000, "lr": 0.0001, "batch_size": 16, "refresh_target_network_freq": 3000, "opt_steps_per_step": 2}, "time_since_restore": 5125.7998015880585, "timesteps_since_restore": 0, "iterations_since_restore": 10}
{"mean_reward": -120.21453835347113, "trial_id": "ee8064fa", "training_iteration": 10, "time_this_iter_s": 531.2995598316193, "done": false, "timesteps_total": null, "episodes_total": null, "experiment_id": "ae7a5e6bac20431bb594eb8184b72316", "date": "2019-11-15_11-00-22", "timestamp": 1573815622, "time_total_s": 5657.099361419678, "pid": 270, "hostname": "213cedb5f1ad", "node_ip": "172.18.0.3", "config": {"replay_size": 10000, "lr": 0.0001, "batch_size": 16, "refresh_target_network_freq": 3000, "opt_steps_per_step": 2}, "time_since_restore": 5657.099361419678, "timesteps_since_restore": 0, "iterations_since_restore": 11}
{"mean_reward": -106.47587043079194, "trial_id": "ee8064fa", "training_iteration": 11, "time_this_iter_s": 499.18876552581787, "done": false, "timesteps_total": null, "episodes_total": null, "experiment_id": "ae7a5e6bac20431bb594eb8184b72316", "date": "2019-11-15_11-08-41", "timestamp": 1573816121, "time_total_s": 6156.288126945496, "pid": 270, "hostname": "213cedb5f1ad", "node_ip": "172.18.0.3", "config": {"replay_size": 10000, "lr": 0.0001, "batch_size": 16, "refresh_target_network_freq": 3000, "opt_steps_per_step": 2}, "time_since_restore": 6156.288126945496, "timesteps_since_restore": 0, "iterations_since_restore": 12}
{"mean_reward": -99.6775211992388, "trial_id": "ee8064fa", "training_iteration": 12, "time_this_iter_s": 500.9393484592438, "done": false, "timesteps_total": null, "episodes_total": null, "experiment_id": "ae7a5e6bac20431bb594eb8184b72316", "date": "2019-11-15_11-17-02", "timestamp": 1573816622, "time_total_s": 6657.227475404739, "pid": 270, "hostname": "213cedb5f1ad", "node_ip": "172.18.0.3", "config": {"replay_size": 10000, "lr": 0.0001, "batch_size": 16, "refresh_target_network_freq": 3000, "opt_steps_per_step": 2}, "time_since_restore": 6657.227475404739, "timesteps_since_restore": 0, "iterations_since_restore": 13}
{"mean_reward": -78.34255532157609, "trial_id": "ee8064fa", "training_iteration": 13, "time_this_iter_s": 534.1987597942352, "done": false, "timesteps_total": null, "episodes_total": null, "experiment_id": "ae7a5e6bac20431bb594eb8184b72316", "date": "2019-11-15_11-25-56", "timestamp": 1573817156, "time_total_s": 7191.426235198975, "pid": 270, "hostname": "213cedb5f1ad", "node_ip": "172.18.0.3", "config": {"replay_size": 10000, "lr": 0.0001, "batch_size": 16, "refresh_target_network_freq": 3000, "opt_steps_per_step": 2}, "time_since_restore": 7191.426235198975, "timesteps_since_restore": 0, "iterations_since_restore": 14}
{"mean_reward": -99.14843543821966, "trial_id": "ee8064fa", "training_iteration": 14, "time_this_iter_s": 498.83279633522034, "done": false, "timesteps_total": null, "episodes_total": null, "experiment_id": "ae7a5e6bac20431bb594eb8184b72316", "date": "2019-11-15_11-34-15", "timestamp": 1573817655, "time_total_s": 7690.259031534195, "pid": 270, "hostname": "213cedb5f1ad", "node_ip": "172.18.0.3", "config": {"replay_size": 10000, "lr": 0.0001, "batch_size": 16, "refresh_target_network_freq": 3000, "opt_steps_per_step": 2}, "time_since_restore": 7690.259031534195, "timesteps_since_restore": 0, "iterations_since_restore": 15}
{"mean_reward": -101.43964857526605, "trial_id": "ee8064fa", "training_iteration": 15, "time_this_iter_s": 502.20158672332764, "done": false, "timesteps_total": null, "episodes_total": null, "experiment_id": "ae7a5e6bac20431bb594eb8184b72316", "date": "2019-11-15_11-42-37", "timestamp": 1573818157, "time_total_s": 8192.460618257523, "pid": 270, "hostname": "213cedb5f1ad", "node_ip": "172.18.0.3", "config": {"replay_size": 10000, "lr": 0.0001, "batch_size": 16, "refresh_target_network_freq": 3000, "opt_steps_per_step": 2}, "time_since_restore": 8192.460618257523, "timesteps_since_restore": 0, "iterations_since_restore": 16}
{"mean_reward": -107.18135382487242, "trial_id": "ee8064fa", "training_iteration": 16, "time_this_iter_s": 509.654824256897, "done": false, "timesteps_total": null, "episodes_total": null, "experiment_id": "ae7a5e6bac20431bb594eb8184b72316", "date": "2019-11-15_11-51-07", "timestamp": 1573818667, "time_total_s": 8702.11544251442, "pid": 270, "hostname": "213cedb5f1ad", "node_ip": "172.18.0.3", "config": {"replay_size": 10000, "lr": 0.0001, "batch_size": 16, "refresh_target_network_freq": 3000, "opt_steps_per_step": 2}, "time_since_restore": 8702.11544251442, "timesteps_since_restore": 0, "iterations_since_restore": 17}
{"mean_reward": -97.06813663388168, "trial_id": "ee8064fa", "training_iteration": 17, "time_this_iter_s": 500.2717270851135, "done": false, "timesteps_total": null, "episodes_total": null, "experiment_id": "ae7a5e6bac20431bb594eb8184b72316", "date": "2019-11-15_11-59-27", "timestamp": 1573819167, "time_total_s": 9202.387169599533, "pid": 270, "hostname": "213cedb5f1ad", "node_ip": "172.18.0.3", "config": {"replay_size": 10000, "lr": 0.0001, "batch_size": 16, "refresh_target_network_freq": 3000, "opt_steps_per_step": 2}, "time_since_restore": 9202.387169599533, "timesteps_since_restore": 0, "iterations_since_restore": 18}
{"mean_reward": -96.38233127526804, "trial_id": "ee8064fa", "training_iteration": 18, "time_this_iter_s": 501.0858042240143, "done": false, "timesteps_total": null, "episodes_total": null, "experiment_id": "ae7a5e6bac20431bb594eb8184b72316", "date": "2019-11-15_12-07-48", "timestamp": 1573819668, "time_total_s": 9703.472973823547, "pid": 270, "hostname": "213cedb5f1ad", "node_ip": "172.18.0.3", "config": {"replay_size": 10000, "lr": 0.0001, "batch_size": 16, "refresh_target_network_freq": 3000, "opt_steps_per_step": 2}, "time_since_restore": 9703.472973823547, "timesteps_since_restore": 0, "iterations_since_restore": 19}
{"mean_reward": -96.84920688378708, "trial_id": "ee8064fa", "training_iteration": 19, "time_this_iter_s": 501.18776679039, "done": false, "timesteps_total": null, "episodes_total": null, "experiment_id": "ae7a5e6bac20431bb594eb8184b72316", "date": "2019-11-15_12-16-10", "timestamp": 1573820170, "time_total_s": 10204.660740613937, "pid": 270, "hostname": "213cedb5f1ad", "node_ip": "172.18.0.3", "config": {"replay_size": 10000, "lr": 0.0001, "batch_size": 16, "refresh_target_network_freq": 3000, "opt_steps_per_step": 2}, "time_since_restore": 10204.660740613937, "timesteps_since_restore": 0, "iterations_since_restore": 20}
{"mean_reward": -103.40001947823737, "trial_id": "ee8064fa", "training_iteration": 20, "time_this_iter_s": 503.0020685195923, "done": false, "timesteps_total": null, "episodes_total": null, "experiment_id": "ae7a5e6bac20431bb594eb8184b72316", "date": "2019-11-15_12-24-33", "timestamp": 1573820673, "time_total_s": 10707.66280913353, "pid": 270, "hostname": "213cedb5f1ad", "node_ip": "172.18.0.3", "config": {"replay_size": 10000, "lr": 0.0001, "batch_size": 16, "refresh_target_network_freq": 3000, "opt_steps_per_step": 2}, "time_since_restore": 10707.66280913353, "timesteps_since_restore": 0, "iterations_since_restore": 21}
{"mean_reward": -81.36445044949814, "trial_id": "ee8064fa", "training_iteration": 21, "time_this_iter_s": 508.81997656822205, "done": false, "timesteps_total": null, "episodes_total": null, "experiment_id": "ae7a5e6bac20431bb594eb8184b72316", "date": "2019-11-15_12-33-01", "timestamp": 1573821181, "time_total_s": 11216.482785701752, "pid": 270, "hostname": "213cedb5f1ad", "node_ip": "172.18.0.3", "config": {"replay_size": 10000, "lr": 0.0001, "batch_size": 16, "refresh_target_network_freq": 3000, "opt_steps_per_step": 2}, "time_since_restore": 11216.482785701752, "timesteps_since_restore": 0, "iterations_since_restore": 22}
{"mean_reward": -10.456168678758498, "trial_id": "ee8064fa", "training_iteration": 22, "time_this_iter_s": 526.6981127262115, "done": false, "timesteps_total": null, "episodes_total": null, "experiment_id": "ae7a5e6bac20431bb594eb8184b72316", "date": "2019-11-15_12-41-48", "timestamp": 1573821708, "time_total_s": 11743.180898427963, "pid": 270, "hostname": "213cedb5f1ad", "node_ip": "172.18.0.3", "config": {"replay_size": 10000, "lr": 0.0001, "batch_size": 16, "refresh_target_network_freq": 3000, "opt_steps_per_step": 2}, "time_since_restore": 11743.180898427963, "timesteps_since_restore": 0, "iterations_since_restore": 23}
{"mean_reward": -106.20426807029422, "trial_id": "ee8064fa", "training_iteration": 23, "time_this_iter_s": 500.8159532546997, "done": false, "timesteps_total": null, "episodes_total": null, "experiment_id": "ae7a5e6bac20431bb594eb8184b72316", "date": "2019-11-15_12-50-09", "timestamp": 1573822209, "time_total_s": 12243.996851682663, "pid": 270, "hostname": "213cedb5f1ad", "node_ip": "172.18.0.3", "config": {"replay_size": 10000, "lr": 0.0001, "batch_size": 16, "refresh_target_network_freq": 3000, "opt_steps_per_step": 2}, "time_since_restore": 12243.996851682663, "timesteps_since_restore": 0, "iterations_since_restore": 24}
{"mean_reward": -52.98391260555161, "trial_id": "ee8064fa", "training_iteration": 24, "time_this_iter_s": 523.7662692070007, "done": false, "timesteps_total": null, "episodes_total": null, "experiment_id": "ae7a5e6bac20431bb594eb8184b72316", "date": "2019-11-15_12-58-53", "timestamp": 1573822733, "time_total_s": 12767.763120889664, "pid": 270, "hostname": "213cedb5f1ad", "node_ip": "172.18.0.3", "config": {"replay_size": 10000, "lr": 0.0001, "batch_size": 16, "refresh_target_network_freq": 3000, "opt_steps_per_step": 2}, "time_since_restore": 12767.763120889664, "timesteps_since_restore": 0, "iterations_since_restore": 25}
{"mean_reward": -82.40476237059308, "trial_id": "ee8064fa", "training_iteration": 25, "time_this_iter_s": 515.4724273681641, "done": false, "timesteps_total": null, "episodes_total": null, "experiment_id": "ae7a5e6bac20431bb594eb8184b72316", "date": "2019-11-15_13-07-28", "timestamp": 1573823248, "time_total_s": 13283.235548257828, "pid": 270, "hostname": "213cedb5f1ad", "node_ip": "172.18.0.3", "config": {"replay_size": 10000, "lr": 0.0001, "batch_size": 16, "refresh_target_network_freq": 3000, "opt_steps_per_step": 2}, "time_since_restore": 13283.235548257828, "timesteps_since_restore": 0, "iterations_since_restore": 26}
{"mean_reward": -67.68838724197111, "trial_id": "ee8064fa", "training_iteration": 26, "time_this_iter_s": 511.9366202354431, "done": false, "timesteps_total": null, "episodes_total": null, "experiment_id": "ae7a5e6bac20431bb594eb8184b72316", "date": "2019-11-15_13-16-00", "timestamp": 1573823760, "time_total_s": 13795.17216849327, "pid": 270, "hostname": "213cedb5f1ad", "node_ip": "172.18.0.3", "config": {"replay_size": 10000, "lr": 0.0001, "batch_size": 16, "refresh_target_network_freq": 3000, "opt_steps_per_step": 2}, "time_since_restore": 13795.17216849327, "timesteps_since_restore": 0, "iterations_since_restore": 27}
{"mean_reward": -33.0142346247049, "trial_id": "ee8064fa", "training_iteration": 27, "time_this_iter_s": 518.4308731555939, "done": false, "timesteps_total": null, "episodes_total": null, "experiment_id": "ae7a5e6bac20431bb594eb8184b72316", "date": "2019-11-15_13-24-38", "timestamp": 1573824278, "time_total_s": 14313.603041648865, "pid": 270, "hostname": "213cedb5f1ad", "node_ip": "172.18.0.3", "config": {"replay_size": 10000, "lr": 0.0001, "batch_size": 16, "refresh_target_network_freq": 3000, "opt_steps_per_step": 2}, "time_since_restore": 14313.603041648865, "timesteps_since_restore": 0, "iterations_since_restore": 28}
{"mean_reward": 48.766813268774854, "trial_id": "ee8064fa", "training_iteration": 28, "time_this_iter_s": 526.3001797199249, "done": false, "timesteps_total": null, "episodes_total": null, "experiment_id": "ae7a5e6bac20431bb594eb8184b72316", "date": "2019-11-15_13-33-25", "timestamp": 1573824805, "time_total_s": 14839.90322136879, "pid": 270, "hostname": "213cedb5f1ad", "node_ip": "172.18.0.3", "config": {"replay_size": 10000, "lr": 0.0001, "batch_size": 16, "refresh_target_network_freq": 3000, "opt_steps_per_step": 2}, "time_since_restore": 14839.90322136879, "timesteps_since_restore": 0, "iterations_since_restore": 29}
{"mean_reward": 61.87166139001528, "trial_id": "ee8064fa", "training_iteration": 29, "time_this_iter_s": 526.4077470302582, "done": false, "timesteps_total": null, "episodes_total": null, "experiment_id": "ae7a5e6bac20431bb594eb8184b72316", "date": "2019-11-15_13-42-11", "timestamp": 1573825331, "time_total_s": 15366.310968399048, "pid": 270, "hostname": "213cedb5f1ad", "node_ip": "172.18.0.3", "config": {"replay_size": 10000, "lr": 0.0001, "batch_size": 16, "refresh_target_network_freq": 3000, "opt_steps_per_step": 2}, "time_since_restore": 15366.310968399048, "timesteps_since_restore": 0, "iterations_since_restore": 30}
{"mean_reward": 98.64162273958236, "trial_id": "ee8064fa", "training_iteration": 30, "time_this_iter_s": 527.0268640518188, "done": false, "timesteps_total": null, "episodes_total": null, "experiment_id": "ae7a5e6bac20431bb594eb8184b72316", "date": "2019-11-15_13-50-58", "timestamp": 1573825858, "time_total_s": 15893.337832450867, "pid": 270, "hostname": "213cedb5f1ad", "node_ip": "172.18.0.3", "config": {"replay_size": 10000, "lr": 0.0001, "batch_size": 16, "refresh_target_network_freq": 3000, "opt_steps_per_step": 2}, "time_since_restore": 15893.337832450867, "timesteps_since_restore": 0, "iterations_since_restore": 31}
{"mean_reward": -45.50449107436128, "trial_id": "ee8064fa", "training_iteration": 31, "time_this_iter_s": 511.0785551071167, "done": false, "timesteps_total": null, "episodes_total": null, "experiment_id": "ae7a5e6bac20431bb594eb8184b72316", "date": "2019-11-15_13-59-29", "timestamp": 1573826369, "time_total_s": 16404.416387557983, "pid": 270, "hostname": "213cedb5f1ad", "node_ip": "172.18.0.3", "config": {"replay_size": 10000, "lr": 0.0001, "batch_size": 16, "refresh_target_network_freq": 3000, "opt_steps_per_step": 2}, "time_since_restore": 16404.416387557983, "timesteps_since_restore": 0, "iterations_since_restore": 32}
{"mean_reward": -89.72871071005075, "trial_id": "ee8064fa", "training_iteration": 32, "time_this_iter_s": 502.21085143089294, "done": false, "timesteps_total": null, "episodes_total": null, "experiment_id": "ae7a5e6bac20431bb594eb8184b72316", "date": "2019-11-15_14-07-52", "timestamp": 1573826872, "time_total_s": 16906.627238988876, "pid": 270, "hostname": "213cedb5f1ad", "node_ip": "172.18.0.3", "config": {"replay_size": 10000, "lr": 0.0001, "batch_size": 16, "refresh_target_network_freq": 3000, "opt_steps_per_step": 2}, "time_since_restore": 16906.627238988876, "timesteps_since_restore": 0, "iterations_since_restore": 33}
{"mean_reward": 21.950144941986924, "trial_id": "ee8064fa", "training_iteration": 33, "time_this_iter_s": 519.2749366760254, "done": false, "timesteps_total": null, "episodes_total": null, "experiment_id": "ae7a5e6bac20431bb594eb8184b72316", "date": "2019-11-15_14-16-31", "timestamp": 1573827391, "time_total_s": 17425.9021756649, "pid": 270, "hostname": "213cedb5f1ad", "node_ip": "172.18.0.3", "config": {"replay_size": 10000, "lr": 0.0001, "batch_size": 16, "refresh_target_network_freq": 3000, "opt_steps_per_step": 2}, "time_since_restore": 17425.9021756649, "timesteps_since_restore": 0, "iterations_since_restore": 34}
{"mean_reward": -92.59661135273986, "trial_id": "ee8064fa", "training_iteration": 34, "time_this_iter_s": 507.1158814430237, "done": false, "timesteps_total": null, "episodes_total": null, "experiment_id": "ae7a5e6bac20431bb594eb8184b72316", "date": "2019-11-15_14-24-58", "timestamp": 1573827898, "time_total_s": 17933.018057107925, "pid": 270, "hostname": "213cedb5f1ad", "node_ip": "172.18.0.3", "config": {"replay_size": 10000, "lr": 0.0001, "batch_size": 16, "refresh_target_network_freq": 3000, "opt_steps_per_step": 2}, "time_since_restore": 17933.018057107925, "timesteps_since_restore": 0, "iterations_since_restore": 35}
{"mean_reward": -67.35226213285499, "trial_id": "ee8064fa", "training_iteration": 35, "time_this_iter_s": 510.5813138484955, "done": false, "timesteps_total": null, "episodes_total": null, "experiment_id": "ae7a5e6bac20431bb594eb8184b72316", "date": "2019-11-15_14-33-28", "timestamp": 1573828408, "time_total_s": 18443.59937095642, "pid": 270, "hostname": "213cedb5f1ad", "node_ip": "172.18.0.3", "config": {"replay_size": 10000, "lr": 0.0001, "batch_size": 16, "refresh_target_network_freq": 3000, "opt_steps_per_step": 2}, "time_since_restore": 18443.59937095642, "timesteps_since_restore": 0, "iterations_since_restore": 36}
{"mean_reward": -32.49573034517013, "trial_id": "ee8064fa", "training_iteration": 36, "time_this_iter_s": 515.2300152778625, "done": false, "timesteps_total": null, "episodes_total": null, "experiment_id": "ae7a5e6bac20431bb594eb8184b72316", "date": "2019-11-15_14-42-04", "timestamp": 1573828924, "time_total_s": 18958.829386234283, "pid": 270, "hostname": "213cedb5f1ad", "node_ip": "172.18.0.3", "config": {"replay_size": 10000, "lr": 0.0001, "batch_size": 16, "refresh_target_network_freq": 3000, "opt_steps_per_step": 2}, "time_since_restore": 18958.829386234283, "timesteps_since_restore": 0, "iterations_since_restore": 37}
{"mean_reward": -99.67062667972387, "trial_id": "ee8064fa", "training_iteration": 37, "time_this_iter_s": 510.90007495880127, "done": false, "timesteps_total": null, "episodes_total": null, "experiment_id": "ae7a5e6bac20431bb594eb8184b72316", "date": "2019-11-15_14-50-35", "timestamp": 1573829435, "time_total_s": 19469.729461193085, "pid": 270, "hostname": "213cedb5f1ad", "node_ip": "172.18.0.3", "config": {"replay_size": 10000, "lr": 0.0001, "batch_size": 16, "refresh_target_network_freq": 3000, "opt_steps_per_step": 2}, "time_since_restore": 19469.729461193085, "timesteps_since_restore": 0, "iterations_since_restore": 38}
{"mean_reward": -80.87218690373628, "trial_id": "ee8064fa", "training_iteration": 38, "time_this_iter_s": 506.79236483573914, "done": false, "timesteps_total": null, "episodes_total": null, "experiment_id": "ae7a5e6bac20431bb594eb8184b72316", "date": "2019-11-15_14-59-01", "timestamp": 1573829941, "time_total_s": 19976.521826028824, "pid": 270, "hostname": "213cedb5f1ad", "node_ip": "172.18.0.3", "config": {"replay_size": 10000, "lr": 0.0001, "batch_size": 16, "refresh_target_network_freq": 3000, "opt_steps_per_step": 2}, "time_since_restore": 19976.521826028824, "timesteps_since_restore": 0, "iterations_since_restore": 39}
{"mean_reward": 21.127630036597406, "trial_id": "ee8064fa", "training_iteration": 39, "time_this_iter_s": 522.5113382339478, "done": false, "timesteps_total": null, "episodes_total": null, "experiment_id": "ae7a5e6bac20431bb594eb8184b72316", "date": "2019-11-15_15-07-44", "timestamp": 1573830464, "time_total_s": 20499.03316426277, "pid": 270, "hostname": "213cedb5f1ad", "node_ip": "172.18.0.3", "config": {"replay_size": 10000, "lr": 0.0001, "batch_size": 16, "refresh_target_network_freq": 3000, "opt_steps_per_step": 2}, "time_since_restore": 20499.03316426277, "timesteps_since_restore": 0, "iterations_since_restore": 40}
{"mean_reward": -54.47674004184464, "trial_id": "ee8064fa", "training_iteration": 40, "time_this_iter_s": 520.3371784687042, "done": false, "timesteps_total": null, "episodes_total": null, "experiment_id": "ae7a5e6bac20431bb594eb8184b72316", "date": "2019-11-15_15-16-24", "timestamp": 1573830984, "time_total_s": 21019.370342731476, "pid": 270, "hostname": "213cedb5f1ad", "node_ip": "172.18.0.3", "config": {"replay_size": 10000, "lr": 0.0001, "batch_size": 16, "refresh_target_network_freq": 3000, "opt_steps_per_step": 2}, "time_since_restore": 21019.370342731476, "timesteps_since_restore": 0, "iterations_since_restore": 41}
{"mean_reward": 52.9902155025541, "trial_id": "ee8064fa", "training_iteration": 41, "time_this_iter_s": 519.1185593605042, "done": false, "timesteps_total": null, "episodes_total": null, "experiment_id": "ae7a5e6bac20431bb594eb8184b72316", "date": "2019-11-15_15-25-03", "timestamp": 1573831503, "time_total_s": 21538.48890209198, "pid": 270, "hostname": "213cedb5f1ad", "node_ip": "172.18.0.3", "config": {"replay_size": 10000, "lr": 0.0001, "batch_size": 16, "refresh_target_network_freq": 3000, "opt_steps_per_step": 2}, "time_since_restore": 21538.48890209198, "timesteps_since_restore": 0, "iterations_since_restore": 42}
{"mean_reward": 39.15704869099437, "trial_id": "ee8064fa", "training_iteration": 42, "time_this_iter_s": 526.4083590507507, "done": false, "timesteps_total": null, "episodes_total": null, "experiment_id": "ae7a5e6bac20431bb594eb8184b72316", "date": "2019-11-15_15-33-50", "timestamp": 1573832030, "time_total_s": 22064.89726114273, "pid": 270, "hostname": "213cedb5f1ad", "node_ip": "172.18.0.3", "config": {"replay_size": 10000, "lr": 0.0001, "batch_size": 16, "refresh_target_network_freq": 3000, "opt_steps_per_step": 2}, "time_since_restore": 22064.89726114273, "timesteps_since_restore": 0, "iterations_since_restore": 43}
{"mean_reward": -61.550073062425575, "trial_id": "ee8064fa", "training_iteration": 43, "time_this_iter_s": 518.3704857826233, "done": false, "timesteps_total": null, "episodes_total": null, "experiment_id": "ae7a5e6bac20431bb594eb8184b72316", "date": "2019-11-15_15-42-28", "timestamp": 1573832548, "time_total_s": 22583.267746925354, "pid": 270, "hostname": "213cedb5f1ad", "node_ip": "172.18.0.3", "config": {"replay_size": 10000, "lr": 0.0001, "batch_size": 16, "refresh_target_network_freq": 3000, "opt_steps_per_step": 2}, "time_since_restore": 22583.267746925354, "timesteps_since_restore": 0, "iterations_since_restore": 44}
{"mean_reward": 9.922151869934597, "trial_id": "ee8064fa", "training_iteration": 44, "time_this_iter_s": 523.0657699108124, "done": false, "timesteps_total": null, "episodes_total": null, "experiment_id": "ae7a5e6bac20431bb594eb8184b72316", "date": "2019-11-15_15-51-11", "timestamp": 1573833071, "time_total_s": 23106.333516836166, "pid": 270, "hostname": "213cedb5f1ad", "node_ip": "172.18.0.3", "config": {"replay_size": 10000, "lr": 0.0001, "batch_size": 16, "refresh_target_network_freq": 3000, "opt_steps_per_step": 2}, "time_since_restore": 23106.333516836166, "timesteps_since_restore": 0, "iterations_since_restore": 45}
{"mean_reward": 128.31957802961927, "trial_id": "ee8064fa", "training_iteration": 45, "time_this_iter_s": 522.3146176338196, "done": false, "timesteps_total": null, "episodes_total": null, "experiment_id": "ae7a5e6bac20431bb594eb8184b72316", "date": "2019-11-15_15-59-54", "timestamp": 1573833594, "time_total_s": 23628.648134469986, "pid": 270, "hostname": "213cedb5f1ad", "node_ip": "172.18.0.3", "config": {"replay_size": 10000, "lr": 0.0001, "batch_size": 16, "refresh_target_network_freq": 3000, "opt_steps_per_step": 2}, "time_since_restore": 23628.648134469986, "timesteps_since_restore": 0, "iterations_since_restore": 46}
{"mean_reward": -3.860087704015528, "trial_id": "ee8064fa", "training_iteration": 46, "time_this_iter_s": 519.8542709350586, "done": false, "timesteps_total": null, "episodes_total": null, "experiment_id": "ae7a5e6bac20431bb594eb8184b72316", "date": "2019-11-15_16-08-33", "timestamp": 1573834113, "time_total_s": 24148.502405405045, "pid": 270, "hostname": "213cedb5f1ad", "node_ip": "172.18.0.3", "config": {"replay_size": 10000, "lr": 0.0001, "batch_size": 16, "refresh_target_network_freq": 3000, "opt_steps_per_step": 2}, "time_since_restore": 24148.502405405045, "timesteps_since_restore": 0, "iterations_since_restore": 47}
{"mean_reward": -13.672633202553891, "trial_id": "ee8064fa", "training_iteration": 47, "time_this_iter_s": 510.4654018878937, "done": false, "timesteps_total": null, "episodes_total": null, "experiment_id": "ae7a5e6bac20431bb594eb8184b72316", "date": "2019-11-15_16-17-04", "timestamp": 1573834624, "time_total_s": 24658.96780729294, "pid": 270, "hostname": "213cedb5f1ad", "node_ip": "172.18.0.3", "config": {"replay_size": 10000, "lr": 0.0001, "batch_size": 16, "refresh_target_network_freq": 3000, "opt_steps_per_step": 2}, "time_since_restore": 24658.96780729294, "timesteps_since_restore": 0, "iterations_since_restore": 48}
{"mean_reward": 52.21390729744494, "trial_id": "ee8064fa", "training_iteration": 48, "time_this_iter_s": 523.9092109203339, "done": false, "timesteps_total": null, "episodes_total": null, "experiment_id": "ae7a5e6bac20431bb594eb8184b72316", "date": "2019-11-15_16-25-48", "timestamp": 1573835148, "time_total_s": 25182.877018213272, "pid": 270, "hostname": "213cedb5f1ad", "node_ip": "172.18.0.3", "config": {"replay_size": 10000, "lr": 0.0001, "batch_size": 16, "refresh_target_network_freq": 3000, "opt_steps_per_step": 2}, "time_since_restore": 25182.877018213272, "timesteps_since_restore": 0, "iterations_since_restore": 49}
{"mean_reward": 57.14196554756449, "trial_id": "ee8064fa", "training_iteration": 49, "time_this_iter_s": 520.5217158794403, "done": false, "timesteps_total": null, "episodes_total": null, "experiment_id": "ae7a5e6bac20431bb594eb8184b72316", "date": "2019-11-15_16-34-28", "timestamp": 1573835668, "time_total_s": 25703.398734092712, "pid": 270, "hostname": "213cedb5f1ad", "node_ip": "172.18.0.3", "config": {"replay_size": 10000, "lr": 0.0001, "batch_size": 16, "refresh_target_network_freq": 3000, "opt_steps_per_step": 2}, "time_since_restore": 25703.398734092712, "timesteps_since_restore": 0, "iterations_since_restore": 50}
{"mean_reward": 118.57910805854173, "trial_id": "ee8064fa", "training_iteration": 50, "time_this_iter_s": 529.6336486339569, "done": false, "timesteps_total": null, "episodes_total": null, "experiment_id": "ae7a5e6bac20431bb594eb8184b72316", "date": "2019-11-15_16-43-18", "timestamp": 1573836198, "time_total_s": 26233.03238272667, "pid": 270, "hostname": "213cedb5f1ad", "node_ip": "172.18.0.3", "config": {"replay_size": 10000, "lr": 0.0001, "batch_size": 16, "refresh_target_network_freq": 3000, "opt_steps_per_step": 2}, "time_since_restore": 26233.03238272667, "timesteps_since_restore": 0, "iterations_since_restore": 51}
{"mean_reward": 4.547134533297741, "trial_id": "ee8064fa", "training_iteration": 51, "time_this_iter_s": 524.5641374588013, "done": false, "timesteps_total": null, "episodes_total": null, "experiment_id": "ae7a5e6bac20431bb594eb8184b72316", "date": "2019-11-15_16-52-02", "timestamp": 1573836722, "time_total_s": 26757.59652018547, "pid": 270, "hostname": "213cedb5f1ad", "node_ip": "172.18.0.3", "config": {"replay_size": 10000, "lr": 0.0001, "batch_size": 16, "refresh_target_network_freq": 3000, "opt_steps_per_step": 2}, "time_since_restore": 26757.59652018547, "timesteps_since_restore": 0, "iterations_since_restore": 52}
{"mean_reward": 115.88119753765606, "trial_id": "ee8064fa", "training_iteration": 52, "time_this_iter_s": 529.481139421463, "done": false, "timesteps_total": null, "episodes_total": null, "experiment_id": "ae7a5e6bac20431bb594eb8184b72316", "date": "2019-11-15_17-00-52", "timestamp": 1573837252, "time_total_s": 27287.077659606934, "pid": 270, "hostname": "213cedb5f1ad", "node_ip": "172.18.0.3", "config": {"replay_size": 10000, "lr": 0.0001, "batch_size": 16, "refresh_target_network_freq": 3000, "opt_steps_per_step": 2}, "time_since_restore": 27287.077659606934, "timesteps_since_restore": 0, "iterations_since_restore": 53}
{"mean_reward": 117.29986201301385, "trial_id": "ee8064fa", "training_iteration": 53, "time_this_iter_s": 532.5537974834442, "done": false, "timesteps_total": null, "episodes_total": null, "experiment_id": "ae7a5e6bac20431bb594eb8184b72316", "date": "2019-11-15_17-09-45", "timestamp": 1573837785, "time_total_s": 27819.631457090378, "pid": 270, "hostname": "213cedb5f1ad", "node_ip": "172.18.0.3", "config": {"replay_size": 10000, "lr": 0.0001, "batch_size": 16, "refresh_target_network_freq": 3000, "opt_steps_per_step": 2}, "time_since_restore": 27819.631457090378, "timesteps_since_restore": 0, "iterations_since_restore": 54}
{"mean_reward": -32.8537028015591, "trial_id": "ee8064fa", "training_iteration": 54, "time_this_iter_s": 567.6269676685333, "done": false, "timesteps_total": null, "episodes_total": null, "experiment_id": "ae7a5e6bac20431bb594eb8184b72316", "date": "2019-11-15_17-19-12", "timestamp": 1573838352, "time_total_s": 28387.25842475891, "pid": 270, "hostname": "213cedb5f1ad", "node_ip": "172.18.0.3", "config": {"replay_size": 10000, "lr": 0.0001, "batch_size": 16, "refresh_target_network_freq": 3000, "opt_steps_per_step": 2}, "time_since_restore": 28387.25842475891, "timesteps_since_restore": 0, "iterations_since_restore": 55}
{"mean_reward": 208.1565831044957, "trial_id": "ee8064fa", "training_iteration": 55, "time_this_iter_s": 584.7433340549469, "done": false, "timesteps_total": null, "episodes_total": null, "experiment_id": "ae7a5e6bac20431bb594eb8184b72316", "date": "2019-11-15_17-28-57", "timestamp": 1573838937, "time_total_s": 28972.001758813858, "pid": 270, "hostname": "213cedb5f1ad", "node_ip": "172.18.0.3", "config": {"replay_size": 10000, "lr": 0.0001, "batch_size": 16, "refresh_target_network_freq": 3000, "opt_steps_per_step": 2}, "time_since_restore": 28972.001758813858, "timesteps_since_restore": 0, "iterations_since_restore": 56}
{"mean_reward": 108.99558402182856, "trial_id": "ee8064fa", "training_iteration": 56, "time_this_iter_s": 603.0203542709351, "done": false, "timesteps_total": null, "episodes_total": null, "experiment_id": "ae7a5e6bac20431bb594eb8184b72316", "date": "2019-11-15_17-39-00", "timestamp": 1573839540, "time_total_s": 29575.022113084793, "pid": 270, "hostname": "213cedb5f1ad", "node_ip": "172.18.0.3", "config": {"replay_size": 10000, "lr": 0.0001, "batch_size": 16, "refresh_target_network_freq": 3000, "opt_steps_per_step": 2}, "time_since_restore": 29575.022113084793, "timesteps_since_restore": 0, "iterations_since_restore": 57}
{"mean_reward": -30.76471122728846, "trial_id": "ee8064fa", "training_iteration": 57, "time_this_iter_s": 584.3330984115601, "done": false, "timesteps_total": null, "episodes_total": null, "experiment_id": "ae7a5e6bac20431bb594eb8184b72316", "date": "2019-11-15_17-48-44", "timestamp": 1573840124, "time_total_s": 30159.355211496353, "pid": 270, "hostname": "213cedb5f1ad", "node_ip": "172.18.0.3", "config": {"replay_size": 10000, "lr": 0.0001, "batch_size": 16, "refresh_target_network_freq": 3000, "opt_steps_per_step": 2}, "time_since_restore": 30159.355211496353, "timesteps_since_restore": 0, "iterations_since_restore": 58}
{"mean_reward": -46.50709934132635, "trial_id": "ee8064fa", "training_iteration": 58, "time_this_iter_s": 568.0952167510986, "done": false, "timesteps_total": null, "episodes_total": null, "experiment_id": "ae7a5e6bac20431bb594eb8184b72316", "date": "2019-11-15_17-58-12", "timestamp": 1573840692, "time_total_s": 30727.45042824745, "pid": 270, "hostname": "213cedb5f1ad", "node_ip": "172.18.0.3", "config": {"replay_size": 10000, "lr": 0.0001, "batch_size": 16, "refresh_target_network_freq": 3000, "opt_steps_per_step": 2}, "time_since_restore": 30727.45042824745, "timesteps_since_restore": 0, "iterations_since_restore": 59}
{"mean_reward": -39.039962317824575, "trial_id": "ee8064fa", "training_iteration": 59, "time_this_iter_s": 583.3423290252686, "done": false, "timesteps_total": null, "episodes_total": null, "experiment_id": "ae7a5e6bac20431bb594eb8184b72316", "date": "2019-11-15_18-07-56", "timestamp": 1573841276, "time_total_s": 31310.79275727272, "pid": 270, "hostname": "213cedb5f1ad", "node_ip": "172.18.0.3", "config": {"replay_size": 10000, "lr": 0.0001, "batch_size": 16, "refresh_target_network_freq": 3000, "opt_steps_per_step": 2}, "time_since_restore": 31310.79275727272, "timesteps_since_restore": 0, "iterations_since_restore": 60}
{"mean_reward": -69.53245352399959, "trial_id": "ee8064fa", "training_iteration": 60, "time_this_iter_s": 579.1924495697021, "done": false, "timesteps_total": null, "episodes_total": null, "experiment_id": "ae7a5e6bac20431bb594eb8184b72316", "date": "2019-11-15_18-17-35", "timestamp": 1573841855, "time_total_s": 31889.985206842422, "pid": 270, "hostname": "213cedb5f1ad", "node_ip": "172.18.0.3", "config": {"replay_size": 10000, "lr": 0.0001, "batch_size": 16, "refresh_target_network_freq": 3000, "opt_steps_per_step": 2}, "time_since_restore": 31889.985206842422, "timesteps_since_restore": 0, "iterations_since_restore": 61}
{"mean_reward": -74.33171288188963, "trial_id": "ee8064fa", "training_iteration": 61, "time_this_iter_s": 576.1801106929779, "done": false, "timesteps_total": null, "episodes_total": null, "experiment_id": "ae7a5e6bac20431bb594eb8184b72316", "date": "2019-11-15_18-27-11", "timestamp": 1573842431, "time_total_s": 32466.1653175354, "pid": 270, "hostname": "213cedb5f1ad", "node_ip": "172.18.0.3", "config": {"replay_size": 10000, "lr": 0.0001, "batch_size": 16, "refresh_target_network_freq": 3000, "opt_steps_per_step": 2}, "time_since_restore": 32466.1653175354, "timesteps_since_restore": 0, "iterations_since_restore": 62}
{"mean_reward": -94.057904040693, "trial_id": "ee8064fa", "training_iteration": 62, "time_this_iter_s": 561.5402104854584, "done": false, "timesteps_total": null, "episodes_total": null, "experiment_id": "ae7a5e6bac20431bb594eb8184b72316", "date": "2019-11-15_18-36-33", "timestamp": 1573842993, "time_total_s": 33027.70552802086, "pid": 270, "hostname": "213cedb5f1ad", "node_ip": "172.18.0.3", "config": {"replay_size": 10000, "lr": 0.0001, "batch_size": 16, "refresh_target_network_freq": 3000, "opt_steps_per_step": 2}, "time_since_restore": 33027.70552802086, "timesteps_since_restore": 0, "iterations_since_restore": 63}
{"mean_reward": -20.525909589394598, "trial_id": "ee8064fa", "training_iteration": 63, "time_this_iter_s": 580.1450695991516, "done": false, "timesteps_total": null, "episodes_total": null, "experiment_id": "ae7a5e6bac20431bb594eb8184b72316", "date": "2019-11-15_18-46-13", "timestamp": 1573843573, "time_total_s": 33607.85059762001, "pid": 270, "hostname": "213cedb5f1ad", "node_ip": "172.18.0.3", "config": {"replay_size": 10000, "lr": 0.0001, "batch_size": 16, "refresh_target_network_freq": 3000, "opt_steps_per_step": 2}, "time_since_restore": 33607.85059762001, "timesteps_since_restore": 0, "iterations_since_restore": 64}
{"mean_reward": 203.7228220340219, "trial_id": "ee8064fa", "training_iteration": 64, "time_this_iter_s": 599.6837728023529, "done": false, "timesteps_total": null, "episodes_total": null, "experiment_id": "ae7a5e6bac20431bb594eb8184b72316", "date": "2019-11-15_18-56-12", "timestamp": 1573844172, "time_total_s": 34207.53437042236, "pid": 270, "hostname": "213cedb5f1ad", "node_ip": "172.18.0.3", "config": {"replay_size": 10000, "lr": 0.0001, "batch_size": 16, "refresh_target_network_freq": 3000, "opt_steps_per_step": 2}, "time_since_restore": 34207.53437042236, "timesteps_since_restore": 0, "iterations_since_restore": 65}
{"mean_reward": 71.43169060378007, "trial_id": "ee8064fa", "training_iteration": 65, "time_this_iter_s": 586.6062982082367, "done": false, "timesteps_total": null, "episodes_total": null, "experiment_id": "ae7a5e6bac20431bb594eb8184b72316", "date": "2019-11-15_19-05-59", "timestamp": 1573844759, "time_total_s": 34794.1406686306, "pid": 270, "hostname": "213cedb5f1ad", "node_ip": "172.18.0.3", "config": {"replay_size": 10000, "lr": 0.0001, "batch_size": 16, "refresh_target_network_freq": 3000, "opt_steps_per_step": 2}, "time_since_restore": 34794.1406686306, "timesteps_since_restore": 0, "iterations_since_restore": 66}
{"mean_reward": 258.39063967489807, "trial_id": "ee8064fa", "training_iteration": 66, "time_this_iter_s": 597.6249375343323, "done": false, "timesteps_total": null, "episodes_total": null, "experiment_id": "ae7a5e6bac20431bb594eb8184b72316", "date": "2019-11-15_19-15-57", "timestamp": 1573845357, "time_total_s": 35391.76560616493, "pid": 270, "hostname": "213cedb5f1ad", "node_ip": "172.18.0.3", "config": {"replay_size": 10000, "lr": 0.0001, "batch_size": 16, "refresh_target_network_freq": 3000, "opt_steps_per_step": 2}, "time_since_restore": 35391.76560616493, "timesteps_since_restore": 0, "iterations_since_restore": 67}
{"mean_reward": 250.64540615028682, "trial_id": "ee8064fa", "training_iteration": 67, "time_this_iter_s": 586.4120516777039, "done": false, "timesteps_total": null, "episodes_total": null, "experiment_id": "ae7a5e6bac20431bb594eb8184b72316", "date": "2019-11-15_19-25-43", "timestamp": 1573845943, "time_total_s": 35978.177657842636, "pid": 270, "hostname": "213cedb5f1ad", "node_ip": "172.18.0.3", "config": {"replay_size": 10000, "lr": 0.0001, "batch_size": 16, "refresh_target_network_freq": 3000, "opt_steps_per_step": 2}, "time_since_restore": 35978.177657842636, "timesteps_since_restore": 0, "iterations_since_restore": 68}
{"mean_reward": 267.5322310452572, "trial_id": "ee8064fa", "training_iteration": 68, "time_this_iter_s": 592.9189493656158, "done": false, "timesteps_total": null, "episodes_total": null, "experiment_id": "ae7a5e6bac20431bb594eb8184b72316", "date": "2019-11-15_19-35-36", "timestamp": 1573846536, "time_total_s": 36571.09660720825, "pid": 270, "hostname": "213cedb5f1ad", "node_ip": "172.18.0.3", "config": {"replay_size": 10000, "lr": 0.0001, "batch_size": 16, "refresh_target_network_freq": 3000, "opt_steps_per_step": 2}, "time_since_restore": 36571.09660720825, "timesteps_since_restore": 0, "iterations_since_restore": 69}
{"mean_reward": 138.1125366464783, "trial_id": "ee8064fa", "training_iteration": 69, "time_this_iter_s": 595.017073392868, "done": false, "timesteps_total": null, "episodes_total": null, "experiment_id": "ae7a5e6bac20431bb594eb8184b72316", "date": "2019-11-15_19-45-31", "timestamp": 1573847131, "time_total_s": 37166.11368060112, "pid": 270, "hostname": "213cedb5f1ad", "node_ip": "172.18.0.3", "config": {"replay_size": 10000, "lr": 0.0001, "batch_size": 16, "refresh_target_network_freq": 3000, "opt_steps_per_step": 2}, "time_since_restore": 37166.11368060112, "timesteps_since_restore": 0, "iterations_since_restore": 70}
{"mean_reward": 106.36687661330386, "trial_id": "ee8064fa", "training_iteration": 70, "time_this_iter_s": 599.3258776664734, "done": false, "timesteps_total": null, "episodes_total": null, "experiment_id": "ae7a5e6bac20431bb594eb8184b72316", "date": "2019-11-15_19-55-30", "timestamp": 1573847730, "time_total_s": 37765.43955826759, "pid": 270, "hostname": "213cedb5f1ad", "node_ip": "172.18.0.3", "config": {"replay_size": 10000, "lr": 0.0001, "batch_size": 16, "refresh_target_network_freq": 3000, "opt_steps_per_step": 2}, "time_since_restore": 37765.43955826759, "timesteps_since_restore": 0, "iterations_since_restore": 71}
{"mean_reward": 153.7184144346892, "trial_id": "ee8064fa", "training_iteration": 71, "time_this_iter_s": 597.6683900356293, "done": false, "timesteps_total": null, "episodes_total": null, "experiment_id": "ae7a5e6bac20431bb594eb8184b72316", "date": "2019-11-15_20-05-28", "timestamp": 1573848328, "time_total_s": 38363.10794830322, "pid": 270, "hostname": "213cedb5f1ad", "node_ip": "172.18.0.3", "config": {"replay_size": 10000, "lr": 0.0001, "batch_size": 16, "refresh_target_network_freq": 3000, "opt_steps_per_step": 2}, "time_since_restore": 38363.10794830322, "timesteps_since_restore": 0, "iterations_since_restore": 72}
{"mean_reward": 283.8143994104296, "trial_id": "ee8064fa", "training_iteration": 72, "time_this_iter_s": 594.7248110771179, "done": false, "timesteps_total": null, "episodes_total": null, "experiment_id": "ae7a5e6bac20431bb594eb8184b72316", "date": "2019-11-15_20-15-23", "timestamp": 1573848923, "time_total_s": 38957.83275938034, "pid": 270, "hostname": "213cedb5f1ad", "node_ip": "172.18.0.3", "config": {"replay_size": 10000, "lr": 0.0001, "batch_size": 16, "refresh_target_network_freq": 3000, "opt_steps_per_step": 2}, "time_since_restore": 38957.83275938034, "timesteps_since_restore": 0, "iterations_since_restore": 73}
{"mean_reward": 230.13474814679216, "trial_id": "ee8064fa", "training_iteration": 73, "time_this_iter_s": 596.0861251354218, "done": false, "timesteps_total": null, "episodes_total": null, "experiment_id": "ae7a5e6bac20431bb594eb8184b72316", "date": "2019-11-15_20-25-19", "timestamp": 1573849519, "time_total_s": 39553.91888451576, "pid": 270, "hostname": "213cedb5f1ad", "node_ip": "172.18.0.3", "config": {"replay_size": 10000, "lr": 0.0001, "batch_size": 16, "refresh_target_network_freq": 3000, "opt_steps_per_step": 2}, "time_since_restore": 39553.91888451576, "timesteps_since_restore": 0, "iterations_since_restore": 74}
{"mean_reward": 271.1857716684461, "trial_id": "ee8064fa", "training_iteration": 74, "time_this_iter_s": 609.3633894920349, "done": false, "timesteps_total": null, "episodes_total": null, "experiment_id": "ae7a5e6bac20431bb594eb8184b72316", "date": "2019-11-15_20-35-28", "timestamp": 1573850128, "time_total_s": 40163.2822740078, "pid": 270, "hostname": "213cedb5f1ad", "node_ip": "172.18.0.3", "config": {"replay_size": 10000, "lr": 0.0001, "batch_size": 16, "refresh_target_network_freq": 3000, "opt_steps_per_step": 2}, "time_since_restore": 40163.2822740078, "timesteps_since_restore": 0, "iterations_since_restore": 75}
{"mean_reward": 283.92191117108587, "trial_id": "ee8064fa", "training_iteration": 75, "time_this_iter_s": 594.8694412708282, "done": false, "timesteps_total": null, "episodes_total": null, "experiment_id": "ae7a5e6bac20431bb594eb8184b72316", "date": "2019-11-15_20-45-23", "timestamp": 1573850723, "time_total_s": 40758.151715278625, "pid": 270, "hostname": "213cedb5f1ad", "node_ip": "172.18.0.3", "config": {"replay_size": 10000, "lr": 0.0001, "batch_size": 16, "refresh_target_network_freq": 3000, "opt_steps_per_step": 2}, "time_since_restore": 40758.151715278625, "timesteps_since_restore": 0, "iterations_since_restore": 76}
{"mean_reward": 201.27144804310487, "trial_id": "ee8064fa", "training_iteration": 76, "time_this_iter_s": 585.2363750934601, "done": false, "timesteps_total": null, "episodes_total": null, "experiment_id": "ae7a5e6bac20431bb594eb8184b72316", "date": "2019-11-15_20-55-08", "timestamp": 1573851308, "time_total_s": 41343.388090372086, "pid": 270, "hostname": "213cedb5f1ad", "node_ip": "172.18.0.3", "config": {"replay_size": 10000, "lr": 0.0001, "batch_size": 16, "refresh_target_network_freq": 3000, "opt_steps_per_step": 2}, "time_since_restore": 41343.388090372086, "timesteps_since_restore": 0, "iterations_since_restore": 77}
{"mean_reward": 275.8800153016777, "trial_id": "ee8064fa", "training_iteration": 77, "time_this_iter_s": 598.696408033371, "done": false, "timesteps_total": null, "episodes_total": null, "experiment_id": "ae7a5e6bac20431bb594eb8184b72316", "date": "2019-11-15_21-05-07", "timestamp": 1573851907, "time_total_s": 41942.08449840546, "pid": 270, "hostname": "213cedb5f1ad", "node_ip": "172.18.0.3", "config": {"replay_size": 10000, "lr": 0.0001, "batch_size": 16, "refresh_target_network_freq": 3000, "opt_steps_per_step": 2}, "time_since_restore": 41942.08449840546, "timesteps_since_restore": 0, "iterations_since_restore": 78}
{"mean_reward": 180.69042692028586, "trial_id": "ee8064fa", "training_iteration": 78, "time_this_iter_s": 582.41361951828, "done": false, "timesteps_total": null, "episodes_total": null, "experiment_id": "ae7a5e6bac20431bb594eb8184b72316", "date": "2019-11-15_21-14-49", "timestamp": 1573852489, "time_total_s": 42524.49811792374, "pid": 270, "hostname": "213cedb5f1ad", "node_ip": "172.18.0.3", "config": {"replay_size": 10000, "lr": 0.0001, "batch_size": 16, "refresh_target_network_freq": 3000, "opt_steps_per_step": 2}, "time_since_restore": 42524.49811792374, "timesteps_since_restore": 0, "iterations_since_restore": 79}
{"mean_reward": 284.1699331308484, "trial_id": "ee8064fa", "training_iteration": 79, "time_this_iter_s": 594.7913904190063, "done": false, "timesteps_total": null, "episodes_total": null, "experiment_id": "ae7a5e6bac20431bb594eb8184b72316", "date": "2019-11-15_21-24-44", "timestamp": 1573853084, "time_total_s": 43119.28950834274, "pid": 270, "hostname": "213cedb5f1ad", "node_ip": "172.18.0.3", "config": {"replay_size": 10000, "lr": 0.0001, "batch_size": 16, "refresh_target_network_freq": 3000, "opt_steps_per_step": 2}, "time_since_restore": 43119.28950834274, "timesteps_since_restore": 0, "iterations_since_restore": 80}
{"mean_reward": 283.4190604400978, "trial_id": "ee8064fa", "training_iteration": 80, "time_this_iter_s": 586.3893394470215, "done": false, "timesteps_total": null, "episodes_total": null, "experiment_id": "ae7a5e6bac20431bb594eb8184b72316", "date": "2019-11-15_21-34-31", "timestamp": 1573853671, "time_total_s": 43705.678847789764, "pid": 270, "hostname": "213cedb5f1ad", "node_ip": "172.18.0.3", "config": {"replay_size": 10000, "lr": 0.0001, "batch_size": 16, "refresh_target_network_freq": 3000, "opt_steps_per_step": 2}, "time_since_restore": 43705.678847789764, "timesteps_since_restore": 0, "iterations_since_restore": 81}
{"mean_reward": -14.11171209557429, "trial_id": "ee8064fa", "training_iteration": 81, "time_this_iter_s": 604.7003228664398, "done": false, "timesteps_total": null, "episodes_total": null, "experiment_id": "ae7a5e6bac20431bb594eb8184b72316", "date": "2019-11-15_21-44-35", "timestamp": 1573854275, "time_total_s": 44310.379170656204, "pid": 270, "hostname": "213cedb5f1ad", "node_ip": "172.18.0.3", "config": {"replay_size": 10000, "lr": 0.0001, "batch_size": 16, "refresh_target_network_freq": 3000, "opt_steps_per_step": 2}, "time_since_restore": 44310.379170656204, "timesteps_since_restore": 0, "iterations_since_restore": 82}
{"mean_reward": 284.16420484510877, "trial_id": "ee8064fa", "training_iteration": 82, "time_this_iter_s": 587.2349150180817, "done": false, "timesteps_total": null, "episodes_total": null, "experiment_id": "ae7a5e6bac20431bb594eb8184b72316", "date": "2019-11-15_21-54-22", "timestamp": 1573854862, "time_total_s": 44897.614085674286, "pid": 270, "hostname": "213cedb5f1ad", "node_ip": "172.18.0.3", "config": {"replay_size": 10000, "lr": 0.0001, "batch_size": 16, "refresh_target_network_freq": 3000, "opt_steps_per_step": 2}, "time_since_restore": 44897.614085674286, "timesteps_since_restore": 0, "iterations_since_restore": 83}
{"mean_reward": 290.6693033737225, "trial_id": "ee8064fa", "training_iteration": 83, "time_this_iter_s": 582.9001710414886, "done": false, "timesteps_total": null, "episodes_total": null, "experiment_id": "ae7a5e6bac20431bb594eb8184b72316", "date": "2019-11-15_22-04-05", "timestamp": 1573855445, "time_total_s": 45480.514256715775, "pid": 270, "hostname": "213cedb5f1ad", "node_ip": "172.18.0.3", "config": {"replay_size": 10000, "lr": 0.0001, "batch_size": 16, "refresh_target_network_freq": 3000, "opt_steps_per_step": 2}, "time_since_restore": 45480.514256715775, "timesteps_since_restore": 0, "iterations_since_restore": 84}
{"mean_reward": 260.8672012909836, "trial_id": "ee8064fa", "training_iteration": 84, "time_this_iter_s": 592.4215040206909, "done": false, "timesteps_total": null, "episodes_total": null, "experiment_id": "ae7a5e6bac20431bb594eb8184b72316", "date": "2019-11-15_22-13-58", "timestamp": 1573856038, "time_total_s": 46072.935760736465, "pid": 270, "hostname": "213cedb5f1ad", "node_ip": "172.18.0.3", "config": {"replay_size": 10000, "lr": 0.0001, "batch_size": 16, "refresh_target_network_freq": 3000, "opt_steps_per_step": 2}, "time_since_restore": 46072.935760736465, "timesteps_since_restore": 0, "iterations_since_restore": 85}
{"mean_reward": 225.75378315644426, "trial_id": "ee8064fa", "training_iteration": 85, "time_this_iter_s": 594.7486686706543, "done": false, "timesteps_total": null, "episodes_total": null, "experiment_id": "ae7a5e6bac20431bb594eb8184b72316", "date": "2019-11-15_22-23-53", "timestamp": 1573856633, "time_total_s": 46667.68442940712, "pid": 270, "hostname": "213cedb5f1ad", "node_ip": "172.18.0.3", "config": {"replay_size": 10000, "lr": 0.0001, "batch_size": 16, "refresh_target_network_freq": 3000, "opt_steps_per_step": 2}, "time_since_restore": 46667.68442940712, "timesteps_since_restore": 0, "iterations_since_restore": 86}
{"mean_reward": 157.03671872224166, "trial_id": "ee8064fa", "training_iteration": 86, "time_this_iter_s": 584.7413065433502, "done": false, "timesteps_total": null, "episodes_total": null, "experiment_id": "ae7a5e6bac20431bb594eb8184b72316", "date": "2019-11-15_22-33-37", "timestamp": 1573857217, "time_total_s": 47252.42573595047, "pid": 270, "hostname": "213cedb5f1ad", "node_ip": "172.18.0.3", "config": {"replay_size": 10000, "lr": 0.0001, "batch_size": 16, "refresh_target_network_freq": 3000, "opt_steps_per_step": 2}, "time_since_restore": 47252.42573595047, "timesteps_since_restore": 0, "iterations_since_restore": 87}
{"mean_reward": 197.69438183579132, "trial_id": "ee8064fa", "training_iteration": 87, "time_this_iter_s": 592.096168756485, "done": false, "timesteps_total": null, "episodes_total": null, "experiment_id": "ae7a5e6bac20431bb594eb8184b72316", "date": "2019-11-15_22-43-29", "timestamp": 1573857809, "time_total_s": 47844.521904706955, "pid": 270, "hostname": "213cedb5f1ad", "node_ip": "172.18.0.3", "config": {"replay_size": 10000, "lr": 0.0001, "batch_size": 16, "refresh_target_network_freq": 3000, "opt_steps_per_step": 2}, "time_since_restore": 47844.521904706955, "timesteps_since_restore": 0, "iterations_since_restore": 88}
{"mean_reward": 231.57449884580964, "trial_id": "ee8064fa", "training_iteration": 88, "time_this_iter_s": 584.7164041996002, "done": false, "timesteps_total": null, "episodes_total": null, "experiment_id": "ae7a5e6bac20431bb594eb8184b72316", "date": "2019-11-15_22-53-14", "timestamp": 1573858394, "time_total_s": 48429.238308906555, "pid": 270, "hostname": "213cedb5f1ad", "node_ip": "172.18.0.3", "config": {"replay_size": 10000, "lr": 0.0001, "batch_size": 16, "refresh_target_network_freq": 3000, "opt_steps_per_step": 2}, "time_since_restore": 48429.238308906555, "timesteps_since_restore": 0, "iterations_since_restore": 89}
{"mean_reward": 255.14325017698152, "trial_id": "ee8064fa", "training_iteration": 89, "time_this_iter_s": 597.3323969841003, "done": false, "timesteps_total": null, "episodes_total": null, "experiment_id": "ae7a5e6bac20431bb594eb8184b72316", "date": "2019-11-15_23-03-11", "timestamp": 1573858991, "time_total_s": 49026.570705890656, "pid": 270, "hostname": "213cedb5f1ad", "node_ip": "172.18.0.3", "config": {"replay_size": 10000, "lr": 0.0001, "batch_size": 16, "refresh_target_network_freq": 3000, "opt_steps_per_step": 2}, "time_since_restore": 49026.570705890656, "timesteps_since_restore": 0, "iterations_since_restore": 90}
{"mean_reward": 282.6959181788513, "trial_id": "ee8064fa", "training_iteration": 90, "time_this_iter_s": 595.6802892684937, "done": false, "timesteps_total": null, "episodes_total": null, "experiment_id": "ae7a5e6bac20431bb594eb8184b72316", "date": "2019-11-15_23-13-07", "timestamp": 1573859587, "time_total_s": 49622.25099515915, "pid": 270, "hostname": "213cedb5f1ad", "node_ip": "172.18.0.3", "config": {"replay_size": 10000, "lr": 0.0001, "batch_size": 16, "refresh_target_network_freq": 3000, "opt_steps_per_step": 2}, "time_since_restore": 49622.25099515915, "timesteps_since_restore": 0, "iterations_since_restore": 91}
{"mean_reward": 267.99341533150226, "trial_id": "ee8064fa", "training_iteration": 91, "time_this_iter_s": 620.2133498191833, "done": false, "timesteps_total": null, "episodes_total": null, "experiment_id": "ae7a5e6bac20431bb594eb8184b72316", "date": "2019-11-15_23-23-27", "timestamp": 1573860207, "time_total_s": 50242.46434497833, "pid": 270, "hostname": "213cedb5f1ad", "node_ip": "172.18.0.3", "config": {"replay_size": 10000, "lr": 0.0001, "batch_size": 16, "refresh_target_network_freq": 3000, "opt_steps_per_step": 2}, "time_since_restore": 50242.46434497833, "timesteps_since_restore": 0, "iterations_since_restore": 92}
{"mean_reward": 152.73859517956194, "trial_id": "ee8064fa", "training_iteration": 92, "time_this_iter_s": 631.9208292961121, "done": false, "timesteps_total": null, "episodes_total": null, "experiment_id": "ae7a5e6bac20431bb594eb8184b72316", "date": "2019-11-15_23-33-59", "timestamp": 1573860839, "time_total_s": 50874.385174274445, "pid": 270, "hostname": "213cedb5f1ad", "node_ip": "172.18.0.3", "config": {"replay_size": 10000, "lr": 0.0001, "batch_size": 16, "refresh_target_network_freq": 3000, "opt_steps_per_step": 2}, "time_since_restore": 50874.385174274445, "timesteps_since_restore": 0, "iterations_since_restore": 93}
{"mean_reward": 235.8034134929029, "trial_id": "ee8064fa", "training_iteration": 93, "time_this_iter_s": 662.4332675933838, "done": false, "timesteps_total": null, "episodes_total": null, "experiment_id": "ae7a5e6bac20431bb594eb8184b72316", "date": "2019-11-15_23-45-02", "timestamp": 1573861502, "time_total_s": 51536.81844186783, "pid": 270, "hostname": "213cedb5f1ad", "node_ip": "172.18.0.3", "config": {"replay_size": 10000, "lr": 0.0001, "batch_size": 16, "refresh_target_network_freq": 3000, "opt_steps_per_step": 2}, "time_since_restore": 51536.81844186783, "timesteps_since_restore": 0, "iterations_since_restore": 94}
{"mean_reward": 123.70223604310858, "trial_id": "ee8064fa", "training_iteration": 94, "time_this_iter_s": 688.4448482990265, "done": false, "timesteps_total": null, "episodes_total": null, "experiment_id": "ae7a5e6bac20431bb594eb8184b72316", "date": "2019-11-15_23-56-30", "timestamp": 1573862190, "time_total_s": 52225.263290166855, "pid": 270, "hostname": "213cedb5f1ad", "node_ip": "172.18.0.3", "config": {"replay_size": 10000, "lr": 0.0001, "batch_size": 16, "refresh_target_network_freq": 3000, "opt_steps_per_step": 2}, "time_since_restore": 52225.263290166855, "timesteps_since_restore": 0, "iterations_since_restore": 95}
{"mean_reward": 268.77351000237826, "trial_id": "ee8064fa", "training_iteration": 95, "time_this_iter_s": 663.807275056839, "done": false, "timesteps_total": null, "episodes_total": null, "experiment_id": "ae7a5e6bac20431bb594eb8184b72316", "date": "2019-11-16_00-07-34", "timestamp": 1573862854, "time_total_s": 52889.070565223694, "pid": 270, "hostname": "213cedb5f1ad", "node_ip": "172.18.0.3", "config": {"replay_size": 10000, "lr": 0.0001, "batch_size": 16, "refresh_target_network_freq": 3000, "opt_steps_per_step": 2}, "time_since_restore": 52889.070565223694, "timesteps_since_restore": 0, "iterations_since_restore": 96}
{"mean_reward": 241.0457439177545, "trial_id": "ee8064fa", "training_iteration": 96, "time_this_iter_s": 684.7416133880615, "done": false, "timesteps_total": null, "episodes_total": null, "experiment_id": "ae7a5e6bac20431bb594eb8184b72316", "date": "2019-11-16_00-18-59", "timestamp": 1573863539, "time_total_s": 53573.812178611755, "pid": 270, "hostname": "213cedb5f1ad", "node_ip": "172.18.0.3", "config": {"replay_size": 10000, "lr": 0.0001, "batch_size": 16, "refresh_target_network_freq": 3000, "opt_steps_per_step": 2}, "time_since_restore": 53573.812178611755, "timesteps_since_restore": 0, "iterations_since_restore": 97}
{"mean_reward": 286.0179663836214, "trial_id": "ee8064fa", "training_iteration": 97, "time_this_iter_s": 644.2630543708801, "done": false, "timesteps_total": null, "episodes_total": null, "experiment_id": "ae7a5e6bac20431bb594eb8184b72316", "date": "2019-11-16_00-29-43", "timestamp": 1573864183, "time_total_s": 54218.075232982635, "pid": 270, "hostname": "213cedb5f1ad", "node_ip": "172.18.0.3", "config": {"replay_size": 10000, "lr": 0.0001, "batch_size": 16, "refresh_target_network_freq": 3000, "opt_steps_per_step": 2}, "time_since_restore": 54218.075232982635, "timesteps_since_restore": 0, "iterations_since_restore": 98}
{"mean_reward": 136.68617960249998, "trial_id": "ee8064fa", "training_iteration": 98, "time_this_iter_s": 630.2278583049774, "done": false, "timesteps_total": null, "episodes_total": null, "experiment_id": "ae7a5e6bac20431bb594eb8184b72316", "date": "2019-11-16_00-40-13", "timestamp": 1573864813, "time_total_s": 54848.30309128761, "pid": 270, "hostname": "213cedb5f1ad", "node_ip": "172.18.0.3", "config": {"replay_size": 10000, "lr": 0.0001, "batch_size": 16, "refresh_target_network_freq": 3000, "opt_steps_per_step": 2}, "time_since_restore": 54848.30309128761, "timesteps_since_restore": 0, "iterations_since_restore": 99}
{"mean_reward": 296.0789980535819, "trial_id": "ee8064fa", "training_iteration": 99, "time_this_iter_s": 617.0905721187592, "done": false, "timesteps_total": null, "episodes_total": null, "experiment_id": "ae7a5e6bac20431bb594eb8184b72316", "date": "2019-11-16_00-50-30", "timestamp": 1573865430, "time_total_s": 55465.39366340637, "pid": 270, "hostname": "213cedb5f1ad", "node_ip": "172.18.0.3", "config": {"replay_size": 10000, "lr": 0.0001, "batch_size": 16, "refresh_target_network_freq": 3000, "opt_steps_per_step": 2}, "time_since_restore": 55465.39366340637, "timesteps_since_restore": 0, "iterations_since_restore": 100}
